[
  {
    "title": "XQuery 3.1: An XML Query Language",
    "shortlink": "https://www.w3.org/TR/xquery-31/",
    "shortname": "xquery-31",
    "description": "<p>XQuery 3.1 is a versatile query and application development language,\r\ncapable of processing the information content of diverse data sources\r\nincluding structured and semi-structured documents, relational databases\r\nand tree-bases databases. The XQuery language is designed to support\r\npowerful optimizations and pre-compilation leading to very efficient\r\nsearches over large amounts of data, including over so-called XML-native\r\ndatabases that read and write XML but have an efficient internal\r\nstorage.</p>",
    "_links": {
      "self": {
        "href": "https://api.w3.org/specifications/xquery-31"
      },
      "version-history": {
        "href": "https://api.w3.org/specifications/xquery-31/versions"
      },
      "first-version": {
        "href": "https://api.w3.org/specifications/xquery-31/versions/20140424",
        "title": "Working Draft"
      },
      "latest-version": {
        "href": "https://api.w3.org/specifications/xquery-31/versions/20170117",
        "title": "Proposed Recommendation"
      }
    },
    "versions": [
      {
        "status": "Proposed Recommendation",
        "rec-track": true,
        "uri": "https://www.w3.org/TR/2017/PR-xquery-31-20170117/",
        "date": "2017-01-17",
        "pr-reviews-due": "2017-02-28",
        "informative": false,
        "title": "XQuery 3.1: An XML Query Language",
        "shortlink": "https://www.w3.org/TR/xquery-31/",
        "process-rules": "https://www.w3.org/2015/Process-20150901/",
        "_links": {
          "self": {
            "href": "https://api.w3.org/specifications/xquery-31/versions/20170117"
          },
          "editors": {
            "href": "https://api.w3.org/specifications/xquery-31/versions/20170117/editors"
          },
          "deliverers": {
            "href": "https://api.w3.org/specifications/xquery-31/versions/20170117/deliverers"
          },
          "specification": {
            "href": "https://api.w3.org/specifications/xquery-31"
          },
          "predecessor-version": {
            "href": "https://api.w3.org/specifications/xquery-31/versions/20170117/predecessors"
          }
        }
      },
      {
        "status": "Candidate Recommendation",
        "rec-track": true,
        "uri": "https://www.w3.org/TR/2016/CR-xquery-31-20161213/",
        "date": "2016-12-13",
        "implementation-feedback-due": "2017-01-10",
        "informative": false,
        "title": "XQuery 3.1: An XML Query Language",
        "shortlink": "https://www.w3.org/TR/xquery-31/",
        "process-rules": "https://www.w3.org/2015/Process-20150901/",
        "_links": {
          "self": {
            "href": "https://api.w3.org/specifications/xquery-31/versions/20161213"
          },
          "editors": {
            "href": "https://api.w3.org/specifications/xquery-31/versions/20161213/editors"
          },
          "deliverers": {
            "href": "https://api.w3.org/specifications/xquery-31/versions/20161213/deliverers"
          },
          "specification": {
            "href": "https://api.w3.org/specifications/xquery-31"
          },
          "predecessor-version": {
            "href": "https://api.w3.org/specifications/xquery-31/versions/20161213/predecessors"
          },
          "successor-version": {
            "href": "https://api.w3.org/specifications/xquery-31/versions/20161213/successors"
          }
        }
      },
      {
        "status": "Candidate Recommendation",
        "rec-track": true,
        "uri": "http://www.w3.org/TR/2015/CR-xquery-31-20151217/",
        "date": "2015-12-17",
        "implementation-feedback-due": "2016-01-31",
        "informative": false,
        "title": "XQuery 3.1: An XML Query Language",
        "shortlink": "http://www.w3.org/TR/xquery-31/",
        "process-rules": "http://www.w3.org/2015/Process-20150901/",
        "_links": {
          "self": {
            "href": "https://api.w3.org/specifications/xquery-31/versions/20151217"
          },
          "editors": {
            "href": "https://api.w3.org/specifications/xquery-31/versions/20151217/editors"
          },
          "deliverers": {
            "href": "https://api.w3.org/specifications/xquery-31/versions/20151217/deliverers"
          },
          "specification": {
            "href": "https://api.w3.org/specifications/xquery-31"
          },
          "predecessor-version": {
            "href": "https://api.w3.org/specifications/xquery-31/versions/20151217/predecessors"
          },
          "successor-version": {
            "href": "https://api.w3.org/specifications/xquery-31/versions/20151217/successors"
          }
        }
      },
      {
        "status": "Candidate Recommendation",
        "rec-track": true,
        "uri": "http://www.w3.org/TR/2014/CR-xquery-31-20141218/",
        "date": "2014-12-18",
        "implementation-feedback-due": "2015-02-13",
        "informative": false,
        "title": "XQuery 3.1: An XML Query Language",
        "shortlink": "http://www.w3.org/TR/xquery-31/",
        "process-rules": "http://www.w3.org/2005/10/Process-20051014/",
        "_links": {
          "self": {
            "href": "https://api.w3.org/specifications/xquery-31/versions/20141218"
          },
          "editors": {
            "href": "https://api.w3.org/specifications/xquery-31/versions/20141218/editors"
          },
          "deliverers": {
            "href": "https://api.w3.org/specifications/xquery-31/versions/20141218/deliverers"
          },
          "specification": {
            "href": "https://api.w3.org/specifications/xquery-31"
          },
          "predecessor-version": {
            "href": "https://api.w3.org/specifications/xquery-31/versions/20141218/predecessors"
          },
          "successor-version": {
            "href": "https://api.w3.org/specifications/xquery-31/versions/20141218/successors"
          }
        }
      },
      {
        "status": "Last Call",
        "rec-track": true,
        "uri": "http://www.w3.org/TR/2014/WD-xquery-31-20141007/",
        "date": "2014-10-07",
        "last-call-feedback-due": "2014-11-07",
        "informative": false,
        "title": "XQuery 3.1: An XML Query Language",
        "shortlink": "http://www.w3.org/TR/xquery-31/",
        "process-rules": "http://www.w3.org/2005/10/Process-20051014/",
        "_links": {
          "self": {
            "href": "https://api.w3.org/specifications/xquery-31/versions/20141007"
          },
          "editors": {
            "href": "https://api.w3.org/specifications/xquery-31/versions/20141007/editors"
          },
          "deliverers": {
            "href": "https://api.w3.org/specifications/xquery-31/versions/20141007/deliverers"
          },
          "specification": {
            "href": "https://api.w3.org/specifications/xquery-31"
          },
          "predecessor-version": {
            "href": "https://api.w3.org/specifications/xquery-31/versions/20141007/predecessors"
          },
          "successor-version": {
            "href": "https://api.w3.org/specifications/xquery-31/versions/20141007/successors"
          }
        }
      },
      {
        "status": "Working Draft",
        "rec-track": true,
        "uri": "http://www.w3.org/TR/2014/WD-xquery-31-20140424/",
        "date": "2014-04-24",
        "informative": false,
        "title": "XQuery 3.1: An XML Query Language",
        "shortlink": "http://www.w3.org/TR/xquery-31/",
        "_links": {
          "self": {
            "href": "https://api.w3.org/specifications/xquery-31/versions/20140424"
          },
          "editors": {
            "href": "https://api.w3.org/specifications/xquery-31/versions/20140424/editors"
          },
          "deliverers": {
            "href": "https://api.w3.org/specifications/xquery-31/versions/20140424/deliverers"
          },
          "specification": {
            "href": "https://api.w3.org/specifications/xquery-31"
          },
          "successor-version": {
            "href": "https://api.w3.org/specifications/xquery-31/versions/20140424/successors"
          }
        }
      }
    ]
  },
  {
    "title": "XQuery Scripting Extension 1.0 Requirements",
    "shortlink": "http://www.w3.org/TR/xquery-sx-10-requirements",
    "shortname": "xquery-sx-10-requirements",
    "description": "<p>This document specifies goals and requirements for the XQuery Scripting Extension.</p>",
    "_links": {
      "self": {
        "href": "https://api.w3.org/specifications/xquery-sx-10-requirements"
      },
      "version-history": {
        "href": "https://api.w3.org/specifications/xquery-sx-10-requirements/versions"
      },
      "first-version": {
        "href": "https://api.w3.org/specifications/xquery-sx-10-requirements/versions/20070323",
        "title": "Working Draft"
      },
      "latest-version": {
        "href": "https://api.w3.org/specifications/xquery-sx-10-requirements/versions/20070323",
        "title": "Working Draft"
      }
    },
    "versions": [
      {
        "status": "Working Draft",
        "rec-track": true,
        "uri": "http://www.w3.org/TR/2007/WD-xquery-sx-10-requirements-20070323",
        "date": "2007-03-23",
        "informative": false,
        "title": "XQuery Scripting Extension 1.0 Requirements",
        "shortlink": "http://www.w3.org/TR/xquery-sx-10-requirements",
        "_links": {
          "self": {
            "href": "https://api.w3.org/specifications/xquery-sx-10-requirements/versions/20070323"
          },
          "editors": {
            "href": "https://api.w3.org/specifications/xquery-sx-10-requirements/versions/20070323/editors"
          },
          "deliverers": {
            "href": "https://api.w3.org/specifications/xquery-sx-10-requirements/versions/20070323/deliverers"
          },
          "specification": {
            "href": "https://api.w3.org/specifications/xquery-sx-10-requirements"
          }
        }
      }
    ]
  },
  {
    "title": "XQuery Scripting Extension 1.0 Use Cases",
    "shortlink": "http://www.w3.org/TR/xquery-sx-10-use-cases/",
    "shortname": "xquery-sx-10-use-cases",
    "description": "<p>This document specifies usage scenarios for the XQuery Scripting Extension.</p>",
    "_links": {
      "self": {
        "href": "https://api.w3.org/specifications/xquery-sx-10-use-cases"
      },
      "version-history": {
        "href": "https://api.w3.org/specifications/xquery-sx-10-use-cases/versions"
      },
      "first-version": {
        "href": "https://api.w3.org/specifications/xquery-sx-10-use-cases/versions/20080328",
        "title": "Working Draft"
      },
      "latest-version": {
        "href": "https://api.w3.org/specifications/xquery-sx-10-use-cases/versions/20081203",
        "title": "Working Draft"
      }
    },
    "versions": [
      {
        "status": "Working Draft",
        "rec-track": false,
        "uri": "http://www.w3.org/TR/2008/WD-xquery-sx-10-use-cases-20081203/",
        "date": "2008-12-03",
        "informative": false,
        "title": "XQuery Scripting Extension 1.0 Use Cases",
        "shortlink": "http://www.w3.org/TR/xquery-sx-10-use-cases/",
        "_links": {
          "self": {
            "href": "https://api.w3.org/specifications/xquery-sx-10-use-cases/versions/20081203"
          },
          "editors": {
            "href": "https://api.w3.org/specifications/xquery-sx-10-use-cases/versions/20081203/editors"
          },
          "deliverers": {
            "href": "https://api.w3.org/specifications/xquery-sx-10-use-cases/versions/20081203/deliverers"
          },
          "specification": {
            "href": "https://api.w3.org/specifications/xquery-sx-10-use-cases"
          },
          "predecessor-version": {
            "href": "https://api.w3.org/specifications/xquery-sx-10-use-cases/versions/20081203/predecessors"
          }
        }
      },
      {
        "status": "Working Draft",
        "rec-track": false,
        "uri": "http://www.w3.org/TR/2008/WD-xquery-sx-10-use-cases-20080328/",
        "date": "2008-03-28",
        "informative": false,
        "title": "XQuery Scripting Extension 1.0 Use Cases",
        "shortlink": "http://www.w3.org/TR/xquery-sx-10-use-cases/",
        "_links": {
          "self": {
            "href": "https://api.w3.org/specifications/xquery-sx-10-use-cases/versions/20080328"
          },
          "editors": {
            "href": "https://api.w3.org/specifications/xquery-sx-10-use-cases/versions/20080328/editors"
          },
          "deliverers": {
            "href": "https://api.w3.org/specifications/xquery-sx-10-use-cases/versions/20080328/deliverers"
          },
          "specification": {
            "href": "https://api.w3.org/specifications/xquery-sx-10-use-cases"
          },
          "successor-version": {
            "href": "https://api.w3.org/specifications/xquery-sx-10-use-cases/versions/20080328/successors"
          }
        }
      }
    ]
  },
  {
    "title": "XQueryX 3.1",
    "shortlink": "https://www.w3.org/TR/xqueryx-31/",
    "shortname": "xqueryx-31",
    "description": "<p>XQueryX 3.1 defines an XML syntax for the semantics defined by XQuery\r\n3.1.</p>",
    "_links": {
      "self": {
        "href": "https://api.w3.org/specifications/xqueryx-31"
      },
      "version-history": {
        "href": "https://api.w3.org/specifications/xqueryx-31/versions"
      },
      "first-version": {
        "href": "https://api.w3.org/specifications/xqueryx-31/versions/20140424",
        "title": "Working Draft"
      },
      "latest-version": {
        "href": "https://api.w3.org/specifications/xqueryx-31/versions/20170117",
        "title": "Proposed Recommendation"
      }
    },
    "versions": [
      {
        "status": "Proposed Recommendation",
        "rec-track": true,
        "uri": "https://www.w3.org/TR/2017/PR-xqueryx-31-20170117/",
        "date": "2017-01-17",
        "pr-reviews-due": "2017-02-28",
        "informative": false,
        "title": "XQueryX 3.1",
        "shortlink": "https://www.w3.org/TR/xqueryx-31/",
        "process-rules": "https://www.w3.org/2015/Process-20150901/",
        "_links": {
          "self": {
            "href": "https://api.w3.org/specifications/xqueryx-31/versions/20170117"
          },
          "editors": {
            "href": "https://api.w3.org/specifications/xqueryx-31/versions/20170117/editors"
          },
          "deliverers": {
            "href": "https://api.w3.org/specifications/xqueryx-31/versions/20170117/deliverers"
          },
          "specification": {
            "href": "https://api.w3.org/specifications/xqueryx-31"
          },
          "predecessor-version": {
            "href": "https://api.w3.org/specifications/xqueryx-31/versions/20170117/predecessors"
          }
        }
      },
      {
        "status": "Candidate Recommendation",
        "rec-track": true,
        "uri": "https://www.w3.org/TR/2016/CR-xqueryx-31-20161213/",
        "date": "2016-12-13",
        "implementation-feedback-due": "2017-01-10",
        "informative": false,
        "title": "XQueryX 3.1",
        "shortlink": "https://www.w3.org/TR/xqueryx-31/",
        "process-rules": "https://www.w3.org/2015/Process-20150901/",
        "_links": {
          "self": {
            "href": "https://api.w3.org/specifications/xqueryx-31/versions/20161213"
          },
          "editors": {
            "href": "https://api.w3.org/specifications/xqueryx-31/versions/20161213/editors"
          },
          "deliverers": {
            "href": "https://api.w3.org/specifications/xqueryx-31/versions/20161213/deliverers"
          },
          "specification": {
            "href": "https://api.w3.org/specifications/xqueryx-31"
          },
          "predecessor-version": {
            "href": "https://api.w3.org/specifications/xqueryx-31/versions/20161213/predecessors"
          },
          "successor-version": {
            "href": "https://api.w3.org/specifications/xqueryx-31/versions/20161213/successors"
          }
        }
      },
      {
        "status": "Candidate Recommendation",
        "rec-track": true,
        "uri": "http://www.w3.org/TR/2014/CR-xqueryx-31-20141218/",
        "date": "2014-12-18",
        "implementation-feedback-due": "2015-02-13",
        "informative": false,
        "title": "XQueryX 3.1",
        "shortlink": "http://www.w3.org/TR/xqueryx-31/",
        "process-rules": "http://www.w3.org/2005/10/Process-20051014/",
        "_links": {
          "self": {
            "href": "https://api.w3.org/specifications/xqueryx-31/versions/20141218"
          },
          "editors": {
            "href": "https://api.w3.org/specifications/xqueryx-31/versions/20141218/editors"
          },
          "deliverers": {
            "href": "https://api.w3.org/specifications/xqueryx-31/versions/20141218/deliverers"
          },
          "specification": {
            "href": "https://api.w3.org/specifications/xqueryx-31"
          },
          "predecessor-version": {
            "href": "https://api.w3.org/specifications/xqueryx-31/versions/20141218/predecessors"
          },
          "successor-version": {
            "href": "https://api.w3.org/specifications/xqueryx-31/versions/20141218/successors"
          }
        }
      },
      {
        "status": "Last Call",
        "rec-track": true,
        "uri": "http://www.w3.org/TR/2014/WD-xqueryx-31-20141007/",
        "date": "2014-10-07",
        "last-call-feedback-due": "2014-11-07",
        "informative": false,
        "title": "XQueryX 3.1",
        "shortlink": "http://www.w3.org/TR/xqueryx-31/",
        "process-rules": "http://www.w3.org/2005/10/Process-20051014/",
        "_links": {
          "self": {
            "href": "https://api.w3.org/specifications/xqueryx-31/versions/20141007"
          },
          "editors": {
            "href": "https://api.w3.org/specifications/xqueryx-31/versions/20141007/editors"
          },
          "deliverers": {
            "href": "https://api.w3.org/specifications/xqueryx-31/versions/20141007/deliverers"
          },
          "specification": {
            "href": "https://api.w3.org/specifications/xqueryx-31"
          },
          "predecessor-version": {
            "href": "https://api.w3.org/specifications/xqueryx-31/versions/20141007/predecessors"
          },
          "successor-version": {
            "href": "https://api.w3.org/specifications/xqueryx-31/versions/20141007/successors"
          }
        }
      },
      {
        "status": "Working Draft",
        "rec-track": true,
        "uri": "http://www.w3.org/TR/2014/WD-xqueryx-31-20140424/",
        "date": "2014-04-24",
        "informative": false,
        "title": "XQueryX 3.1",
        "shortlink": "http://www.w3.org/TR/xqueryx-31/",
        "_links": {
          "self": {
            "href": "https://api.w3.org/specifications/xqueryx-31/versions/20140424"
          },
          "editors": {
            "href": "https://api.w3.org/specifications/xqueryx-31/versions/20140424/editors"
          },
          "deliverers": {
            "href": "https://api.w3.org/specifications/xqueryx-31/versions/20140424/deliverers"
          },
          "specification": {
            "href": "https://api.w3.org/specifications/xqueryx-31"
          },
          "successor-version": {
            "href": "https://api.w3.org/specifications/xqueryx-31/versions/20140424/successors"
          }
        }
      }
    ]
  }
]