[
  null,
  null,
  null,
  {
    "shortlink": "https://www.w3.org/TR/css-2023/",
    "description": "<p>This document collects together into one definition all the specs that together form the current state of Cascading Style Sheets (CSS) as of 2023. The primary audience is CSS implementers, not CSS authors, as this definition includes modules by specification stability, not Web browser adoption rate.</p>",
    "title": "CSS Snapshot 2023",
    "shortname": "css-2023",
    "editor-draft": "https://drafts.csswg.org/css-2023/",
    "series-version": "2023",
    "_links": {
      "self": {
        "href": "https://api.w3.org/specifications/css-2023"
      },
      "version-history": {
        "href": "https://api.w3.org/specifications/css-2023/versions"
      },
      "first-version": {
        "href": "https://api.w3.org/specifications/css-2023/versions/20230214",
        "title": "Draft Note"
      },
      "latest-version": {
        "href": "https://api.w3.org/specifications/css-2023/versions/20230214",
        "title": "Draft Note"
      },
      "series": {
        "href": "https://api.w3.org/specification-series/CSS"
      }
    },
    "editorsdraft": "https://drafts.csswg.org/css-2023/",
    "versions": [
      {
        "status": "Draft Note",
        "rec-track": false,
        "editor-draft": "https://drafts.csswg.org/css-2023/",
        "uri": "https://www.w3.org/TR/2023/DNOTE-css-2023-20230214/",
        "date": "2023-02-14",
        "informative": true,
        "title": "CSS Snapshot 2023",
        "shortlink": "https://www.w3.org/TR/css-2023/",
        "process-rules": "https://www.w3.org/2021/Process-20211102/",
        "_links": {
          "self": {
            "href": "https://api.w3.org/specifications/css-2023/versions/20230214"
          },
          "editors": {
            "href": "https://api.w3.org/specifications/css-2023/versions/20230214/editors"
          },
          "deliverers": {
            "href": "https://api.w3.org/specifications/css-2023/versions/20230214/deliverers"
          },
          "specification": {
            "href": "https://api.w3.org/specifications/css-2023"
          }
        }
      }
    ]
  },
  null,
  null,
  {
    "shortlink": "https://www.w3.org/TR/css-animation-worklet-1/",
    "description": "<p>The Animation Worklet API provides a method to create scripted animations that control a set of animation effects. The API is designed to make it possible for user agents to run such animations in their own dedicated thread to provide a degree of performance isolation from main thread.</p>",
    "title": "CSS Animation Worklet API",
    "shortname": "css-animation-worklet-1",
    "editor-draft": "https://drafts.css-houdini.org/css-animationworklet-1/",
    "_links": {
      "self": {
        "href": "https://api.w3.org/specifications/css-animation-worklet-1"
      },
      "version-history": {
        "href": "https://api.w3.org/specifications/css-animation-worklet-1/versions"
      },
      "first-version": {
        "href": "https://api.w3.org/specifications/css-animation-worklet-1/versions/20190625",
        "title": "First Public Working Draft"
      },
      "latest-version": {
        "href": "https://api.w3.org/specifications/css-animation-worklet-1/versions/20190625",
        "title": "First Public Working Draft"
      },
      "series": {
        "href": "https://api.w3.org/specification-series/css-animation-worklet"
      }
    },
    "editorsdraft": "https://drafts.css-houdini.org/css-animationworklet-1/",
    "versions": [
      {
        "status": "First Public Working Draft",
        "rec-track": true,
        "editor-draft": "https://drafts.css-houdini.org/css-animationworklet-1/",
        "uri": "https://www.w3.org/TR/2019/WD-css-animation-worklet-1-20190625/",
        "date": "2019-06-25",
        "informative": false,
        "title": "CSS Animation Worklet API",
        "shortlink": "https://www.w3.org/TR/css-animation-worklet-1/",
        "process-rules": "https://www.w3.org/2019/Process-20190301/",
        "_links": {
          "self": {
            "href": "https://api.w3.org/specifications/css-animation-worklet-1/versions/20190625"
          },
          "editors": {
            "href": "https://api.w3.org/specifications/css-animation-worklet-1/versions/20190625/editors"
          },
          "deliverers": {
            "href": "https://api.w3.org/specifications/css-animation-worklet-1/versions/20190625/deliverers"
          },
          "specification": {
            "href": "https://api.w3.org/specifications/css-animation-worklet-1"
          }
        }
      }
    ]
  },
  null,
  null,
  null,
  null,
  null,
  null,
  null,
  null,
  null,
  null,
  null,
  null,
  null,
  null,
  null,
  null,
  null,
  null,
  null,
  null,
  null,
  null,
  null,
  null,
  null,
  null,
  null,
  null,
  null,
  null,
  null,
  null,
  null,
  null,
  null,
  null,
  null,
  null,
  null,
  null,
  null,
  null,
  null,
  null,
  null,
  null,
  null,
  null,
  null,
  null,
  null,
  null,
  null,
  null,
  null,
  null,
  null,
  null,
  null,
  null,
  null,
  null
]