[
  {
    "shortlink": "https://www.w3.org/TR/alreq/",
    "description": "<p>This document describes requirements for the layout and presentation of text in languages that use the Arabic script when they are used by Web standards and technologies, such as HTML, CSS, Mobile Web, Digital Publications, and Unicode.</p>",
    "title": "Text Layout Requirements for the Arabic Script",
    "shortname": "alreq",
    "editor-draft": "https://w3c.github.io/alreq/",
    "_links": {
      "self": {
        "href": "https://api.w3.org/specifications/alreq"
      },
      "version-history": {
        "href": "https://api.w3.org/specifications/alreq/versions"
      },
      "first-version": {
        "href": "https://api.w3.org/specifications/alreq/versions/20180222",
        "title": "Working Draft"
      },
      "latest-version": {
        "href": "https://api.w3.org/specifications/alreq/versions/20180222",
        "title": "Working Draft"
      }
    },
    "editorsdraft": "https://w3c.github.io/alreq/",
    "versions": [
      {
        "status": "Working Draft",
        "rec-track": false,
        "editor-draft": "https://w3c.github.io/alreq/",
        "uri": "https://www.w3.org/TR/2018/WD-alreq-20180222/",
        "date": "2018-02-22",
        "informative": false,
        "title": "Text Layout Requirements for the Arabic Script",
        "shortlink": "https://www.w3.org/TR/alreq/",
        "process-rules": "https://www.w3.org/2018/Process-20180201/",
        "_links": {
          "self": {
            "href": "https://api.w3.org/specifications/alreq/versions/20180222"
          },
          "editors": {
            "href": "https://api.w3.org/specifications/alreq/versions/20180222/editors"
          },
          "deliverers": {
            "href": "https://api.w3.org/specifications/alreq/versions/20180222/deliverers"
          },
          "specification": {
            "href": "https://api.w3.org/specifications/alreq"
          }
        }
      }
    ]
  },
  {
    "shortlink": "http://www.w3.org/TR/charmod-resid/",
    "description": "<p>Architectural Specification providing authors of specifications, software developers, and content developers with a common reference for the use of resource identifiers building on Unicode.</p>",
    "title": "Character Model for the World Wide Web 1.0: Resource Identifiers",
    "shortname": "charmod-resid",
    "_links": {
      "self": {
        "href": "https://api.w3.org/specifications/charmod-resid"
      },
      "version-history": {
        "href": "https://api.w3.org/specifications/charmod-resid/versions"
      },
      "first-version": {
        "href": "https://api.w3.org/specifications/charmod-resid/versions/20041122",
        "title": "Candidate Recommendation"
      },
      "latest-version": {
        "href": "https://api.w3.org/specifications/charmod-resid/versions/20041122",
        "title": "Candidate Recommendation"
      }
    },
    "versions": [
      {
        "status": "Candidate Recommendation",
        "rec-track": false,
        "uri": "http://www.w3.org/TR/2004/CR-charmod-resid-20041122/",
        "date": "2004-11-22",
        "implementation-feedback-due": "2005-01-15",
        "informative": false,
        "title": "Character Model for the World Wide Web 1.0: Resource Identifiers",
        "shortlink": "http://www.w3.org/TR/charmod-resid/",
        "_links": {
          "self": {
            "href": "https://api.w3.org/specifications/charmod-resid/versions/20041122"
          },
          "editors": {
            "href": "https://api.w3.org/specifications/charmod-resid/versions/20041122/editors"
          },
          "deliverers": {
            "href": "https://api.w3.org/specifications/charmod-resid/versions/20041122/deliverers"
          },
          "specification": {
            "href": "https://api.w3.org/specifications/charmod-resid"
          },
          "predecessor-version": {
            "href": "https://api.w3.org/specifications/charmod-resid/versions/20041122/predecessors"
          }
        }
      },
      {
        "status": "Last Call",
        "rec-track": false,
        "uri": "http://www.w3.org/TR/2004/WD-charmod-20040225/",
        "date": "2004-02-25",
        "last-call-feedback-due": "2004-03-19",
        "informative": false,
        "title": "Character Model for the World Wide Web 1.0: Fundamentals",
        "shortlink": "http://www.w3.org/TR/charmod/",
        "_links": {
          "self": {
            "href": "https://api.w3.org/specifications/charmod/versions/20040225"
          },
          "editors": {
            "href": "https://api.w3.org/specifications/charmod/versions/20040225/editors"
          },
          "deliverers": {
            "href": "https://api.w3.org/specifications/charmod/versions/20040225/deliverers"
          },
          "specification": {
            "href": "https://api.w3.org/specifications/charmod"
          },
          "predecessor-version": {
            "href": "https://api.w3.org/specifications/charmod/versions/20040225/predecessors"
          },
          "successor-version": {
            "href": "https://api.w3.org/specifications/charmod/versions/20040225/successors"
          }
        }
      },
      {
        "status": "Working Draft",
        "rec-track": false,
        "uri": "http://www.w3.org/TR/2003/WD-charmod-20030822/",
        "date": "2003-08-22",
        "informative": false,
        "title": "Character Model for the World Wide Web 1.0",
        "shortlink": "http://www.w3.org/TR/charmod/",
        "_links": {
          "self": {
            "href": "https://api.w3.org/specifications/charmod/versions/20030822"
          },
          "editors": {
            "href": "https://api.w3.org/specifications/charmod/versions/20030822/editors"
          },
          "deliverers": {
            "href": "https://api.w3.org/specifications/charmod/versions/20030822/deliverers"
          },
          "specification": {
            "href": "https://api.w3.org/specifications/charmod"
          },
          "predecessor-version": {
            "href": "https://api.w3.org/specifications/charmod/versions/20030822/predecessors"
          },
          "successor-version": {
            "href": "https://api.w3.org/specifications/charmod/versions/20030822/successors"
          }
        }
      },
      {
        "status": "Last Call",
        "rec-track": false,
        "uri": "http://www.w3.org/TR/2002/WD-charmod-20020430/",
        "date": "2002-04-30",
        "informative": false,
        "title": "Character Model for the World Wide Web 1.0",
        "shortlink": "http://www.w3.org/TR/charmod/",
        "_links": {
          "self": {
            "href": "https://api.w3.org/specifications/charmod/versions/20020430"
          },
          "editors": {
            "href": "https://api.w3.org/specifications/charmod/versions/20020430/editors"
          },
          "deliverers": {
            "href": "https://api.w3.org/specifications/charmod/versions/20020430/deliverers"
          },
          "specification": {
            "href": "https://api.w3.org/specifications/charmod"
          },
          "predecessor-version": {
            "href": "https://api.w3.org/specifications/charmod/versions/20020430/predecessors"
          },
          "successor-version": {
            "href": "https://api.w3.org/specifications/charmod/versions/20020430/successors"
          }
        }
      },
      {
        "status": "Working Draft",
        "rec-track": false,
        "uri": "http://www.w3.org/TR/2002/WD-charmod-20020220/",
        "date": "2002-02-20",
        "informative": false,
        "title": "Character Model for the World Wide Web",
        "shortlink": "http://www.w3.org/TR/charmod/",
        "_links": {
          "self": {
            "href": "https://api.w3.org/specifications/charmod/versions/20020220"
          },
          "editors": {
            "href": "https://api.w3.org/specifications/charmod/versions/20020220/editors"
          },
          "deliverers": {
            "href": "https://api.w3.org/specifications/charmod/versions/20020220/deliverers"
          },
          "specification": {
            "href": "https://api.w3.org/specifications/charmod"
          },
          "predecessor-version": {
            "href": "https://api.w3.org/specifications/charmod/versions/20020220/predecessors"
          },
          "successor-version": {
            "href": "https://api.w3.org/specifications/charmod/versions/20020220/successors"
          }
        }
      },
      {
        "status": "Working Draft",
        "rec-track": false,
        "uri": "http://www.w3.org/TR/2001/WD-charmod-20011220/",
        "date": "2001-12-20",
        "informative": false,
        "title": "Character Model for the World Wide Web 1.0: Fundamentals",
        "shortlink": "http://www.w3.org/TR/charmod/",
        "_links": {
          "self": {
            "href": "https://api.w3.org/specifications/charmod/versions/20011220"
          },
          "editors": {
            "href": "https://api.w3.org/specifications/charmod/versions/20011220/editors"
          },
          "deliverers": {
            "href": "https://api.w3.org/specifications/charmod/versions/20011220/deliverers"
          },
          "specification": {
            "href": "https://api.w3.org/specifications/charmod"
          },
          "predecessor-version": {
            "href": "https://api.w3.org/specifications/charmod/versions/20011220/predecessors"
          },
          "successor-version": {
            "href": "https://api.w3.org/specifications/charmod/versions/20011220/successors"
          }
        }
      },
      {
        "status": "Working Draft",
        "rec-track": false,
        "uri": "http://www.w3.org/TR/2001/WD-charmod-20010928/",
        "date": "2001-09-28",
        "informative": false,
        "title": "Character Model for the World Wide Web 1.0: Fundamentals",
        "shortlink": "http://www.w3.org/TR/charmod/",
        "_links": {
          "self": {
            "href": "https://api.w3.org/specifications/charmod/versions/20010928"
          },
          "editors": {
            "href": "https://api.w3.org/specifications/charmod/versions/20010928/editors"
          },
          "deliverers": {
            "href": "https://api.w3.org/specifications/charmod/versions/20010928/deliverers"
          },
          "specification": {
            "href": "https://api.w3.org/specifications/charmod"
          },
          "predecessor-version": {
            "href": "https://api.w3.org/specifications/charmod/versions/20010928/predecessors"
          },
          "successor-version": {
            "href": "https://api.w3.org/specifications/charmod/versions/20010928/successors"
          }
        }
      },
      {
        "status": "Last Call",
        "rec-track": false,
        "uri": "http://www.w3.org/TR/2001/WD-charmod-20010126/",
        "date": "2001-01-26",
        "informative": false,
        "title": "Character Model for the World Wide Web 1.0: Fundamentals",
        "shortlink": "http://www.w3.org/TR/charmod/",
        "_links": {
          "self": {
            "href": "https://api.w3.org/specifications/charmod/versions/20010126"
          },
          "editors": {
            "href": "https://api.w3.org/specifications/charmod/versions/20010126/editors"
          },
          "deliverers": {
            "href": "https://api.w3.org/specifications/charmod/versions/20010126/deliverers"
          },
          "specification": {
            "href": "https://api.w3.org/specifications/charmod"
          },
          "predecessor-version": {
            "href": "https://api.w3.org/specifications/charmod/versions/20010126/predecessors"
          },
          "successor-version": {
            "href": "https://api.w3.org/specifications/charmod/versions/20010126/successors"
          }
        }
      },
      {
        "status": "Working Draft",
        "rec-track": false,
        "uri": "http://www.w3.org/TR/1999/WD-charmod-19991129/",
        "date": "1999-11-29",
        "informative": false,
        "title": "Character Model for the World Wide Web 1.0: Fundamentals",
        "shortlink": "http://www.w3.org/TR/charmod/",
        "_links": {
          "self": {
            "href": "https://api.w3.org/specifications/charmod/versions/19991129"
          },
          "editors": {
            "href": "https://api.w3.org/specifications/charmod/versions/19991129/editors"
          },
          "deliverers": {
            "href": "https://api.w3.org/specifications/charmod/versions/19991129/deliverers"
          },
          "specification": {
            "href": "https://api.w3.org/specifications/charmod"
          },
          "predecessor-version": {
            "href": "https://api.w3.org/specifications/charmod/versions/19991129/predecessors"
          },
          "successor-version": {
            "href": "https://api.w3.org/specifications/charmod/versions/19991129/successors"
          }
        }
      },
      {
        "status": "Working Draft",
        "rec-track": false,
        "uri": "http://www.w3.org/TR/1999/WD-charmod-19990225",
        "date": "1999-02-25",
        "informative": false,
        "title": "Character Model for the World Wide Web 1.0: Fundamentals",
        "shortlink": "http://www.w3.org/TR/charmod/",
        "_links": {
          "self": {
            "href": "https://api.w3.org/specifications/charmod/versions/19990225"
          },
          "editors": {
            "href": "https://api.w3.org/specifications/charmod/versions/19990225/editors"
          },
          "deliverers": {
            "href": "https://api.w3.org/specifications/charmod/versions/19990225/deliverers"
          },
          "specification": {
            "href": "https://api.w3.org/specifications/charmod"
          },
          "successor-version": {
            "href": "https://api.w3.org/specifications/charmod/versions/19990225/successors"
          }
        }
      }
    ]
  },
  {
    "shortlink": "https://www.w3.org/TR/clreq/",
    "description": "<p>This document summarizes the text composition requirements in the Chinese writing system. One of the goals of the task force is to describe the issues in the Chinese layout requirements, another one is to provide satisfactory equivalent to the current standards (i.e. Unicode), also to promote vendors to implement those relevant features correctly.</p>",
    "title": "Requirements for Chinese Text Layout 中文排版需求",
    "shortname": "clreq",
    "editor-draft": "https://w3c.github.io/clreq/",
    "_links": {
      "self": {
        "href": "https://api.w3.org/specifications/clreq"
      },
      "version-history": {
        "href": "https://api.w3.org/specifications/clreq/versions"
      },
      "first-version": {
        "href": "https://api.w3.org/specifications/clreq/versions/20150723",
        "title": "Working Draft"
      },
      "latest-version": {
        "href": "https://api.w3.org/specifications/clreq/versions/20181220",
        "title": "Working Draft"
      }
    },
    "editorsdraft": "https://w3c.github.io/clreq/",
    "versions": [
      {
        "status": "Working Draft",
        "rec-track": false,
        "editor-draft": "https://w3c.github.io/clreq/",
        "uri": "https://www.w3.org/TR/2018/WD-clreq-20181220/",
        "date": "2018-12-20",
        "informative": false,
        "title": "Requirements for Chinese Text Layout 中文排版需求",
        "shortlink": "https://www.w3.org/TR/clreq/",
        "process-rules": "https://www.w3.org/2018/Process-20180201/",
        "_links": {
          "self": {
            "href": "https://api.w3.org/specifications/clreq/versions/20181220"
          },
          "editors": {
            "href": "https://api.w3.org/specifications/clreq/versions/20181220/editors"
          },
          "deliverers": {
            "href": "https://api.w3.org/specifications/clreq/versions/20181220/deliverers"
          },
          "specification": {
            "href": "https://api.w3.org/specifications/clreq"
          },
          "predecessor-version": {
            "href": "https://api.w3.org/specifications/clreq/versions/20181220/predecessors"
          }
        }
      },
      {
        "status": "Working Draft",
        "rec-track": false,
        "editor-draft": "https://w3c.github.io/clreq/",
        "uri": "https://www.w3.org/TR/2017/WD-clreq-20171229/",
        "date": "2017-12-29",
        "informative": false,
        "title": "Requirements for Chinese Text Layout 中文排版需求",
        "shortlink": "https://www.w3.org/TR/clreq/",
        "process-rules": "https://www.w3.org/2017/Process-20170301/",
        "_links": {
          "self": {
            "href": "https://api.w3.org/specifications/clreq/versions/20171229"
          },
          "editors": {
            "href": "https://api.w3.org/specifications/clreq/versions/20171229/editors"
          },
          "deliverers": {
            "href": "https://api.w3.org/specifications/clreq/versions/20171229/deliverers"
          },
          "specification": {
            "href": "https://api.w3.org/specifications/clreq"
          },
          "predecessor-version": {
            "href": "https://api.w3.org/specifications/clreq/versions/20171229/predecessors"
          },
          "successor-version": {
            "href": "https://api.w3.org/specifications/clreq/versions/20171229/successors"
          }
        }
      },
      {
        "status": "Working Draft",
        "rec-track": false,
        "editor-draft": "https://w3c.github.io/clreq/",
        "uri": "https://www.w3.org/TR/2017/WD-clreq-20170220/",
        "date": "2017-02-20",
        "informative": false,
        "title": "Requirements for Chinese Text Layout 中文排版需求",
        "shortlink": "https://www.w3.org/TR/clreq/",
        "process-rules": "https://www.w3.org/2015/Process-20150901/",
        "_links": {
          "self": {
            "href": "https://api.w3.org/specifications/clreq/versions/20170220"
          },
          "editors": {
            "href": "https://api.w3.org/specifications/clreq/versions/20170220/editors"
          },
          "deliverers": {
            "href": "https://api.w3.org/specifications/clreq/versions/20170220/deliverers"
          },
          "specification": {
            "href": "https://api.w3.org/specifications/clreq"
          },
          "predecessor-version": {
            "href": "https://api.w3.org/specifications/clreq/versions/20170220/predecessors"
          },
          "successor-version": {
            "href": "https://api.w3.org/specifications/clreq/versions/20170220/successors"
          }
        }
      },
      {
        "status": "Working Draft",
        "rec-track": false,
        "editor-draft": "https://w3c.github.io/clreq/",
        "uri": "http://www.w3.org/TR/2015/WD-clreq-20150730/",
        "date": "2015-07-30",
        "informative": false,
        "title": "Requirements for Chinese Text Layout 中文排版需求",
        "shortlink": "http://www.w3.org/TR/clreq/",
        "process-rules": "http://www.w3.org/2014/Process-20140801/",
        "_links": {
          "self": {
            "href": "https://api.w3.org/specifications/clreq/versions/20150730"
          },
          "editors": {
            "href": "https://api.w3.org/specifications/clreq/versions/20150730/editors"
          },
          "deliverers": {
            "href": "https://api.w3.org/specifications/clreq/versions/20150730/deliverers"
          },
          "specification": {
            "href": "https://api.w3.org/specifications/clreq"
          },
          "predecessor-version": {
            "href": "https://api.w3.org/specifications/clreq/versions/20150730/predecessors"
          },
          "successor-version": {
            "href": "https://api.w3.org/specifications/clreq/versions/20150730/successors"
          }
        }
      },
      {
        "status": "Working Draft",
        "rec-track": false,
        "editor-draft": "https://w3c.github.io/clreq/",
        "uri": "http://www.w3.org/TR/2015/WD-clreq-20150723/",
        "date": "2015-07-23",
        "informative": false,
        "title": "Requirements for Chinese Text Layout 中文排版需求",
        "shortlink": "http://www.w3.org/TR/clreq/",
        "process-rules": "http://www.w3.org/2014/Process-20140801/",
        "_links": {
          "self": {
            "href": "https://api.w3.org/specifications/clreq/versions/20150723"
          },
          "editors": {
            "href": "https://api.w3.org/specifications/clreq/versions/20150723/editors"
          },
          "deliverers": {
            "href": "https://api.w3.org/specifications/clreq/versions/20150723/deliverers"
          },
          "specification": {
            "href": "https://api.w3.org/specifications/clreq"
          },
          "successor-version": {
            "href": "https://api.w3.org/specifications/clreq/versions/20150723/successors"
          }
        }
      }
    ]
  },
  {
    "shortlink": "https://www.w3.org/TR/elreq/",
    "description": "<p>This document describes requirements for the layout and presentation of text in languages that use the Ethiopic script when they are used by Web standards and technologies, such as HTML, CSS, Mobile Web, Digital Publications, and Unicode.</p>",
    "title": "Ethiopic Layout Requirements",
    "shortname": "elreq",
    "editor-draft": "https://w3c.github.io/elreq/",
    "_links": {
      "self": {
        "href": "https://api.w3.org/specifications/elreq"
      },
      "version-history": {
        "href": "https://api.w3.org/specifications/elreq/versions"
      },
      "first-version": {
        "href": "https://api.w3.org/specifications/elreq/versions/20160908",
        "title": "Working Draft"
      },
      "latest-version": {
        "href": "https://api.w3.org/specifications/elreq/versions/20161115",
        "title": "Working Draft"
      }
    },
    "editorsdraft": "https://w3c.github.io/elreq/",
    "versions": [
      {
        "status": "Working Draft",
        "rec-track": false,
        "editor-draft": "https://w3c.github.io/elreq/",
        "uri": "https://www.w3.org/TR/2016/WD-elreq-20161115/",
        "date": "2016-11-15",
        "informative": false,
        "title": "Ethiopic Layout Requirements",
        "shortlink": "https://www.w3.org/TR/elreq/",
        "process-rules": "https://www.w3.org/2015/Process-20150901/",
        "_links": {
          "self": {
            "href": "https://api.w3.org/specifications/elreq/versions/20161115"
          },
          "editors": {
            "href": "https://api.w3.org/specifications/elreq/versions/20161115/editors"
          },
          "deliverers": {
            "href": "https://api.w3.org/specifications/elreq/versions/20161115/deliverers"
          },
          "specification": {
            "href": "https://api.w3.org/specifications/elreq"
          },
          "predecessor-version": {
            "href": "https://api.w3.org/specifications/elreq/versions/20161115/predecessors"
          }
        }
      },
      {
        "status": "Working Draft",
        "rec-track": false,
        "editor-draft": "https://w3c.github.io/elreq/",
        "uri": "https://www.w3.org/TR/2016/WD-elreq-20161113/",
        "date": "2016-11-13",
        "informative": false,
        "title": "Ethiopic Layout Requirements",
        "shortlink": "https://www.w3.org/TR/elreq/",
        "process-rules": "https://www.w3.org/2015/Process-20150901/",
        "_links": {
          "self": {
            "href": "https://api.w3.org/specifications/elreq/versions/20161113"
          },
          "editors": {
            "href": "https://api.w3.org/specifications/elreq/versions/20161113/editors"
          },
          "deliverers": {
            "href": "https://api.w3.org/specifications/elreq/versions/20161113/deliverers"
          },
          "specification": {
            "href": "https://api.w3.org/specifications/elreq"
          },
          "predecessor-version": {
            "href": "https://api.w3.org/specifications/elreq/versions/20161113/predecessors"
          },
          "successor-version": {
            "href": "https://api.w3.org/specifications/elreq/versions/20161113/successors"
          }
        }
      },
      {
        "status": "Working Draft",
        "rec-track": false,
        "editor-draft": "https://w3c.github.io/elreq/",
        "uri": "https://www.w3.org/TR/2016/WD-elreq-20161102/",
        "date": "2016-11-02",
        "informative": false,
        "title": "Ethiopic Layout Requirements",
        "shortlink": "https://www.w3.org/TR/elreq/",
        "process-rules": "https://www.w3.org/2015/Process-20150901/",
        "_links": {
          "self": {
            "href": "https://api.w3.org/specifications/elreq/versions/20161102"
          },
          "editors": {
            "href": "https://api.w3.org/specifications/elreq/versions/20161102/editors"
          },
          "deliverers": {
            "href": "https://api.w3.org/specifications/elreq/versions/20161102/deliverers"
          },
          "specification": {
            "href": "https://api.w3.org/specifications/elreq"
          },
          "predecessor-version": {
            "href": "https://api.w3.org/specifications/elreq/versions/20161102/predecessors"
          },
          "successor-version": {
            "href": "https://api.w3.org/specifications/elreq/versions/20161102/successors"
          }
        }
      },
      {
        "status": "Working Draft",
        "rec-track": false,
        "editor-draft": "https://w3c.github.io/elreq/",
        "uri": "https://www.w3.org/TR/2016/WD-elreq-20161017/",
        "date": "2016-10-17",
        "informative": false,
        "title": "Ethiopic Layout Requirements",
        "shortlink": "https://www.w3.org/TR/elreq/",
        "process-rules": "https://www.w3.org/2015/Process-20150901/",
        "_links": {
          "self": {
            "href": "https://api.w3.org/specifications/elreq/versions/20161017"
          },
          "editors": {
            "href": "https://api.w3.org/specifications/elreq/versions/20161017/editors"
          },
          "deliverers": {
            "href": "https://api.w3.org/specifications/elreq/versions/20161017/deliverers"
          },
          "specification": {
            "href": "https://api.w3.org/specifications/elreq"
          },
          "predecessor-version": {
            "href": "https://api.w3.org/specifications/elreq/versions/20161017/predecessors"
          },
          "successor-version": {
            "href": "https://api.w3.org/specifications/elreq/versions/20161017/successors"
          }
        }
      },
      {
        "status": "Working Draft",
        "rec-track": false,
        "editor-draft": "https://w3c.github.io/elreq/",
        "uri": "https://www.w3.org/TR/2016/WD-elreq-20161012/",
        "date": "2016-10-12",
        "informative": false,
        "title": "Ethiopic Layout Requirements",
        "shortlink": "https://www.w3.org/TR/elreq/",
        "process-rules": "https://www.w3.org/2015/Process-20150901/",
        "_links": {
          "self": {
            "href": "https://api.w3.org/specifications/elreq/versions/20161012"
          },
          "editors": {
            "href": "https://api.w3.org/specifications/elreq/versions/20161012/editors"
          },
          "deliverers": {
            "href": "https://api.w3.org/specifications/elreq/versions/20161012/deliverers"
          },
          "specification": {
            "href": "https://api.w3.org/specifications/elreq"
          },
          "predecessor-version": {
            "href": "https://api.w3.org/specifications/elreq/versions/20161012/predecessors"
          },
          "successor-version": {
            "href": "https://api.w3.org/specifications/elreq/versions/20161012/successors"
          }
        }
      },
      {
        "status": "Working Draft",
        "rec-track": false,
        "editor-draft": "https://w3c.github.io/elreq/",
        "uri": "https://www.w3.org/TR/2016/WD-elreq-20160908/",
        "date": "2016-09-08",
        "informative": false,
        "title": "Ethiopic Layout Requirements",
        "shortlink": "https://www.w3.org/TR/elreq/",
        "process-rules": "https://www.w3.org/2015/Process-20150901/",
        "_links": {
          "self": {
            "href": "https://api.w3.org/specifications/elreq/versions/20160908"
          },
          "editors": {
            "href": "https://api.w3.org/specifications/elreq/versions/20160908/editors"
          },
          "deliverers": {
            "href": "https://api.w3.org/specifications/elreq/versions/20160908/deliverers"
          },
          "specification": {
            "href": "https://api.w3.org/specifications/elreq"
          },
          "successor-version": {
            "href": "https://api.w3.org/specifications/elreq/versions/20160908/successors"
          }
        }
      }
    ]
  },
  {
    "shortlink": "https://www.w3.org/TR/encoding/",
    "description": "<p>While encodings have been defined to some extent, implementations have not always implemented them in the same way, have not always used the same labels, and often differ in dealing with undefined and former proprietary areas of encodings. This specification attempts to fill those gaps so that new implementations do not have to reverse engineer encoding implementations of the market leaders and existing implementations can converge.</p>",
    "title": "Encoding",
    "shortname": "encoding",
    "editor-draft": "https://encoding.spec.whatwg.org/",
    "_links": {
      "self": {
        "href": "https://api.w3.org/specifications/encoding"
      },
      "version-history": {
        "href": "https://api.w3.org/specifications/encoding/versions"
      },
      "first-version": {
        "href": "https://api.w3.org/specifications/encoding/versions/20140128",
        "title": "Working Draft"
      },
      "latest-version": {
        "href": "https://api.w3.org/specifications/encoding/versions/20180327",
        "title": "Candidate Recommendation"
      }
    },
    "editorsdraft": "https://encoding.spec.whatwg.org/",
    "versions": [
      {
        "status": "Candidate Recommendation",
        "rec-track": true,
        "editor-draft": "https://encoding.spec.whatwg.org/",
        "uri": "https://www.w3.org/TR/2018/CR-encoding-20180327/",
        "date": "2018-03-27",
        "implementation-feedback-due": "2018-05-27",
        "informative": false,
        "title": "Encoding",
        "shortlink": "https://www.w3.org/TR/encoding/",
        "process-rules": "https://www.w3.org/2018/Process-20180201/",
        "_links": {
          "self": {
            "href": "https://api.w3.org/specifications/encoding/versions/20180327"
          },
          "editors": {
            "href": "https://api.w3.org/specifications/encoding/versions/20180327/editors"
          },
          "deliverers": {
            "href": "https://api.w3.org/specifications/encoding/versions/20180327/deliverers"
          },
          "specification": {
            "href": "https://api.w3.org/specifications/encoding"
          },
          "predecessor-version": {
            "href": "https://api.w3.org/specifications/encoding/versions/20180327/predecessors"
          }
        }
      },
      {
        "status": "Candidate Recommendation",
        "rec-track": true,
        "editor-draft": "https://encoding.spec.whatwg.org/",
        "uri": "https://www.w3.org/TR/2017/CR-encoding-20170413/",
        "date": "2017-04-13",
        "implementation-feedback-due": "2017-06-12",
        "informative": false,
        "title": "Encoding",
        "shortlink": "https://www.w3.org/TR/encoding/",
        "process-rules": "https://www.w3.org/2017/Process-20170301/",
        "_links": {
          "self": {
            "href": "https://api.w3.org/specifications/encoding/versions/20170413"
          },
          "editors": {
            "href": "https://api.w3.org/specifications/encoding/versions/20170413/editors"
          },
          "deliverers": {
            "href": "https://api.w3.org/specifications/encoding/versions/20170413/deliverers"
          },
          "specification": {
            "href": "https://api.w3.org/specifications/encoding"
          },
          "predecessor-version": {
            "href": "https://api.w3.org/specifications/encoding/versions/20170413/predecessors"
          },
          "successor-version": {
            "href": "https://api.w3.org/specifications/encoding/versions/20170413/successors"
          }
        }
      },
      {
        "status": "Candidate Recommendation",
        "rec-track": true,
        "editor-draft": "https://encoding.spec.whatwg.org/",
        "uri": "https://www.w3.org/TR/2016/CR-encoding-20161215/",
        "date": "2016-12-15",
        "implementation-feedback-due": "2016-12-20",
        "informative": false,
        "title": "Encoding",
        "shortlink": "https://www.w3.org/TR/encoding/",
        "process-rules": "https://www.w3.org/2015/Process-20150901/",
        "_links": {
          "self": {
            "href": "https://api.w3.org/specifications/encoding/versions/20161215"
          },
          "editors": {
            "href": "https://api.w3.org/specifications/encoding/versions/20161215/editors"
          },
          "deliverers": {
            "href": "https://api.w3.org/specifications/encoding/versions/20161215/deliverers"
          },
          "specification": {
            "href": "https://api.w3.org/specifications/encoding"
          },
          "predecessor-version": {
            "href": "https://api.w3.org/specifications/encoding/versions/20161215/predecessors"
          },
          "successor-version": {
            "href": "https://api.w3.org/specifications/encoding/versions/20161215/successors"
          }
        }
      },
      {
        "status": "Candidate Recommendation",
        "rec-track": true,
        "editor-draft": "https://encoding.spec.whatwg.org/",
        "uri": "https://www.w3.org/TR/2016/CR-encoding-20161110/",
        "date": "2016-11-10",
        "implementation-feedback-due": "2016-12-20",
        "informative": false,
        "title": "Encoding",
        "shortlink": "https://www.w3.org/TR/encoding/",
        "process-rules": "https://www.w3.org/2015/Process-20150901/",
        "_links": {
          "self": {
            "href": "https://api.w3.org/specifications/encoding/versions/20161110"
          },
          "editors": {
            "href": "https://api.w3.org/specifications/encoding/versions/20161110/editors"
          },
          "deliverers": {
            "href": "https://api.w3.org/specifications/encoding/versions/20161110/deliverers"
          },
          "specification": {
            "href": "https://api.w3.org/specifications/encoding"
          },
          "predecessor-version": {
            "href": "https://api.w3.org/specifications/encoding/versions/20161110/predecessors"
          },
          "successor-version": {
            "href": "https://api.w3.org/specifications/encoding/versions/20161110/successors"
          }
        }
      },
      {
        "status": "Candidate Recommendation",
        "rec-track": true,
        "editor-draft": "https://encoding.spec.whatwg.org/",
        "uri": "http://www.w3.org/TR/2015/CR-encoding-20151020/",
        "date": "2015-10-20",
        "implementation-feedback-due": "2015-11-24",
        "informative": false,
        "title": "Encoding",
        "shortlink": "http://www.w3.org/TR/encoding/",
        "process-rules": "http://www.w3.org/2015/Process-20150901/",
        "_links": {
          "self": {
            "href": "https://api.w3.org/specifications/encoding/versions/20151020"
          },
          "editors": {
            "href": "https://api.w3.org/specifications/encoding/versions/20151020/editors"
          },
          "deliverers": {
            "href": "https://api.w3.org/specifications/encoding/versions/20151020/deliverers"
          },
          "specification": {
            "href": "https://api.w3.org/specifications/encoding"
          },
          "predecessor-version": {
            "href": "https://api.w3.org/specifications/encoding/versions/20151020/predecessors"
          },
          "successor-version": {
            "href": "https://api.w3.org/specifications/encoding/versions/20151020/successors"
          }
        }
      },
      {
        "status": "Candidate Recommendation",
        "rec-track": true,
        "editor-draft": "https://encoding.spec.whatwg.org/",
        "uri": "http://www.w3.org/TR/2014/CR-encoding-20140916/",
        "date": "2014-09-16",
        "implementation-feedback-due": "2015-03-16",
        "informative": false,
        "title": "Encoding",
        "shortlink": "http://www.w3.org/TR/encoding/",
        "process-rules": "http://www.w3.org/2005/10/Process-20051014/",
        "_links": {
          "self": {
            "href": "https://api.w3.org/specifications/encoding/versions/20140916"
          },
          "editors": {
            "href": "https://api.w3.org/specifications/encoding/versions/20140916/editors"
          },
          "deliverers": {
            "href": "https://api.w3.org/specifications/encoding/versions/20140916/deliverers"
          },
          "specification": {
            "href": "https://api.w3.org/specifications/encoding"
          },
          "predecessor-version": {
            "href": "https://api.w3.org/specifications/encoding/versions/20140916/predecessors"
          },
          "successor-version": {
            "href": "https://api.w3.org/specifications/encoding/versions/20140916/successors"
          }
        }
      },
      {
        "status": "Last Call",
        "rec-track": true,
        "editor-draft": "https://encoding.spec.whatwg.org/",
        "uri": "http://www.w3.org/TR/2014/WD-encoding-20140603/",
        "date": "2014-06-03",
        "last-call-feedback-due": "2014-07-01",
        "informative": false,
        "title": "Encoding",
        "shortlink": "http://www.w3.org/TR/encoding/",
        "_links": {
          "self": {
            "href": "https://api.w3.org/specifications/encoding/versions/20140603"
          },
          "editors": {
            "href": "https://api.w3.org/specifications/encoding/versions/20140603/editors"
          },
          "deliverers": {
            "href": "https://api.w3.org/specifications/encoding/versions/20140603/deliverers"
          },
          "specification": {
            "href": "https://api.w3.org/specifications/encoding"
          },
          "predecessor-version": {
            "href": "https://api.w3.org/specifications/encoding/versions/20140603/predecessors"
          },
          "successor-version": {
            "href": "https://api.w3.org/specifications/encoding/versions/20140603/successors"
          }
        }
      },
      {
        "status": "Working Draft",
        "rec-track": true,
        "editor-draft": "https://encoding.spec.whatwg.org/",
        "uri": "http://www.w3.org/TR/2014/WD-encoding-20140128/",
        "date": "2014-01-28",
        "informative": false,
        "title": "Encoding",
        "shortlink": "http://www.w3.org/TR/encoding/",
        "_links": {
          "self": {
            "href": "https://api.w3.org/specifications/encoding/versions/20140128"
          },
          "editors": {
            "href": "https://api.w3.org/specifications/encoding/versions/20140128/editors"
          },
          "deliverers": {
            "href": "https://api.w3.org/specifications/encoding/versions/20140128/deliverers"
          },
          "specification": {
            "href": "https://api.w3.org/specifications/encoding"
          },
          "successor-version": {
            "href": "https://api.w3.org/specifications/encoding/versions/20140128/successors"
          }
        }
      }
    ]
  },
  {
    "shortlink": "https://www.w3.org/TR/ilreq/",
    "description": "<p>This document describes the basic requirements for Indic script layout and text support on the Web and in eBooks. These requirements provide information for Web technologies such as CSS, HTML and SVG about how to support users of Indic scripts. The current document focuses on Devanagari, but there are plans to widen the scope to encompass additional Indian scripts as time goes on.</p>",
    "title": "Indic Layout Requirements",
    "shortname": "ilreq",
    "editor-draft": "https://w3c.github.io/ilreq/",
    "_links": {
      "self": {
        "href": "https://api.w3.org/specifications/ilreq"
      },
      "version-history": {
        "href": "https://api.w3.org/specifications/ilreq/versions"
      },
      "first-version": {
        "href": "https://api.w3.org/specifications/ilreq/versions/20141216",
        "title": "Working Draft"
      },
      "latest-version": {
        "href": "https://api.w3.org/specifications/ilreq/versions/20170220",
        "title": "Working Draft"
      }
    },
    "editorsdraft": "https://w3c.github.io/ilreq/",
    "versions": [
      {
        "status": "Working Draft",
        "rec-track": false,
        "editor-draft": "https://w3c.github.io/ilreq/",
        "uri": "https://www.w3.org/TR/2017/WD-ilreq-20170220/",
        "date": "2017-02-20",
        "informative": false,
        "title": "Indic Layout Requirements",
        "shortlink": "https://www.w3.org/TR/ilreq/",
        "process-rules": "https://www.w3.org/2015/Process-20150901/",
        "_links": {
          "self": {
            "href": "https://api.w3.org/specifications/ilreq/versions/20170220"
          },
          "editors": {
            "href": "https://api.w3.org/specifications/ilreq/versions/20170220/editors"
          },
          "deliverers": {
            "href": "https://api.w3.org/specifications/ilreq/versions/20170220/deliverers"
          },
          "specification": {
            "href": "https://api.w3.org/specifications/ilreq"
          },
          "predecessor-version": {
            "href": "https://api.w3.org/specifications/ilreq/versions/20170220/predecessors"
          }
        }
      },
      {
        "status": "Working Draft",
        "rec-track": false,
        "editor-draft": "https://w3c.github.io/ilreq/",
        "uri": "http://www.w3.org/TR/2015/WD-ilreq-20150721/",
        "date": "2015-07-21",
        "informative": false,
        "title": "Indic Layout Requirements",
        "shortlink": "http://www.w3.org/TR/ilreq/",
        "process-rules": "http://www.w3.org/2014/Process-20140801/",
        "_links": {
          "self": {
            "href": "https://api.w3.org/specifications/ilreq/versions/20150721"
          },
          "editors": {
            "href": "https://api.w3.org/specifications/ilreq/versions/20150721/editors"
          },
          "deliverers": {
            "href": "https://api.w3.org/specifications/ilreq/versions/20150721/deliverers"
          },
          "specification": {
            "href": "https://api.w3.org/specifications/ilreq"
          },
          "predecessor-version": {
            "href": "https://api.w3.org/specifications/ilreq/versions/20150721/predecessors"
          },
          "successor-version": {
            "href": "https://api.w3.org/specifications/ilreq/versions/20150721/successors"
          }
        }
      },
      {
        "status": "Working Draft",
        "rec-track": false,
        "editor-draft": "https://w3c.github.io/ilreq/",
        "uri": "http://www.w3.org/TR/2014/WD-ilreq-20141216/",
        "date": "2014-12-16",
        "informative": true,
        "title": "Indic Layout Requirements",
        "shortlink": "http://www.w3.org/TR/ilreq/",
        "process-rules": "http://www.w3.org/2014/Process-20140801/",
        "_links": {
          "self": {
            "href": "https://api.w3.org/specifications/ilreq/versions/20141216"
          },
          "editors": {
            "href": "https://api.w3.org/specifications/ilreq/versions/20141216/editors"
          },
          "deliverers": {
            "href": "https://api.w3.org/specifications/ilreq/versions/20141216/deliverers"
          },
          "specification": {
            "href": "https://api.w3.org/specifications/ilreq"
          },
          "successor-version": {
            "href": "https://api.w3.org/specifications/ilreq/versions/20141216/successors"
          }
        }
      }
    ]
  },
  {
    "shortlink": "https://www.w3.org/TR/international-specs/",
    "description": "<p>This document provides a checklist of internationalization-related considerations when developing a specification. Most checklist items point to detailed supporting information in other documents. Where such information does not yet exist, it can be given a temporary home in this document. The dynamic page Internationalization Techniques: Developing specifications is automatically generated from this document.</p>",
    "title": "Internationalization Best Practices for Spec Developers",
    "shortname": "international-specs",
    "editor-draft": "https://w3c.github.io/bp-i18n-specdev/",
    "_links": {
      "self": {
        "href": "https://api.w3.org/specifications/international-specs"
      },
      "version-history": {
        "href": "https://api.w3.org/specifications/international-specs/versions"
      },
      "first-version": {
        "href": "https://api.w3.org/specifications/international-specs/versions/20151020",
        "title": "Working Draft"
      },
      "latest-version": {
        "href": "https://api.w3.org/specifications/international-specs/versions/20161007",
        "title": "Working Draft"
      }
    },
    "editorsdraft": "https://w3c.github.io/bp-i18n-specdev/",
    "versions": [
      {
        "status": "Working Draft",
        "rec-track": false,
        "editor-draft": "https://w3c.github.io/bp-i18n-specdev/",
        "uri": "https://www.w3.org/TR/2016/WD-international-specs-20161007/",
        "date": "2016-10-07",
        "informative": false,
        "title": "Internationalization Best Practices for Spec Developers",
        "shortlink": "https://www.w3.org/TR/international-specs/",
        "process-rules": "https://www.w3.org/2015/Process-20150901/",
        "_links": {
          "self": {
            "href": "https://api.w3.org/specifications/international-specs/versions/20161007"
          },
          "editors": {
            "href": "https://api.w3.org/specifications/international-specs/versions/20161007/editors"
          },
          "deliverers": {
            "href": "https://api.w3.org/specifications/international-specs/versions/20161007/deliverers"
          },
          "specification": {
            "href": "https://api.w3.org/specifications/international-specs"
          },
          "predecessor-version": {
            "href": "https://api.w3.org/specifications/international-specs/versions/20161007/predecessors"
          }
        }
      },
      {
        "status": "Working Draft",
        "rec-track": false,
        "editor-draft": "https://w3c.github.io/bp-i18n-specdev/",
        "uri": "https://www.w3.org/TR/2016/WD-international-specs-20160810/",
        "date": "2016-08-10",
        "informative": false,
        "title": "Internationalization Best Practices for Spec Developers",
        "shortlink": "https://www.w3.org/TR/international-specs/",
        "process-rules": "https://www.w3.org/2015/Process-20150901/",
        "_links": {
          "self": {
            "href": "https://api.w3.org/specifications/international-specs/versions/20160810"
          },
          "editors": {
            "href": "https://api.w3.org/specifications/international-specs/versions/20160810/editors"
          },
          "deliverers": {
            "href": "https://api.w3.org/specifications/international-specs/versions/20160810/deliverers"
          },
          "specification": {
            "href": "https://api.w3.org/specifications/international-specs"
          },
          "predecessor-version": {
            "href": "https://api.w3.org/specifications/international-specs/versions/20160810/predecessors"
          },
          "successor-version": {
            "href": "https://api.w3.org/specifications/international-specs/versions/20160810/successors"
          }
        }
      },
      {
        "status": "Working Draft",
        "rec-track": false,
        "editor-draft": "https://w3c.github.io/bp-i18n-specdev/",
        "uri": "http://www.w3.org/TR/2016/WD-international-specs-20160622/",
        "date": "2016-06-22",
        "informative": false,
        "title": "Internationalization Best Practices for Spec Developers",
        "shortlink": "http://www.w3.org/TR/international-specs/",
        "process-rules": "http://www.w3.org/2015/Process-20150901/",
        "_links": {
          "self": {
            "href": "https://api.w3.org/specifications/international-specs/versions/20160622"
          },
          "editors": {
            "href": "https://api.w3.org/specifications/international-specs/versions/20160622/editors"
          },
          "deliverers": {
            "href": "https://api.w3.org/specifications/international-specs/versions/20160622/deliverers"
          },
          "specification": {
            "href": "https://api.w3.org/specifications/international-specs"
          },
          "predecessor-version": {
            "href": "https://api.w3.org/specifications/international-specs/versions/20160622/predecessors"
          },
          "successor-version": {
            "href": "https://api.w3.org/specifications/international-specs/versions/20160622/successors"
          }
        }
      },
      {
        "status": "Working Draft",
        "rec-track": false,
        "editor-draft": "https://w3c.github.io/bp-i18n-specdev/",
        "uri": "http://www.w3.org/TR/2015/WD-international-specs-20151020/",
        "date": "2015-10-20",
        "informative": false,
        "title": "Internationalization Best Practices for Spec Developers",
        "shortlink": "http://www.w3.org/TR/international-specs/",
        "process-rules": "http://www.w3.org/2015/Process-20150901/",
        "_links": {
          "self": {
            "href": "https://api.w3.org/specifications/international-specs/versions/20151020"
          },
          "editors": {
            "href": "https://api.w3.org/specifications/international-specs/versions/20151020/editors"
          },
          "deliverers": {
            "href": "https://api.w3.org/specifications/international-specs/versions/20151020/deliverers"
          },
          "specification": {
            "href": "https://api.w3.org/specifications/international-specs"
          },
          "successor-version": {
            "href": "https://api.w3.org/specifications/international-specs/versions/20151020/successors"
          }
        }
      }
    ]
  },
  {
    "shortlink": "http://www.w3.org/TR/klreq/",
    "description": "<p>This document describes requirements for general Korean language/Hangul text layout and typography realized with technologies like CSS, SVG and XSL-FO. The document is mainly based on a project to develop the international standard for Korean text layout. It is similar in intent to the Japanese Layout Requirements WG Note.</p>",
    "title": "Requirements for Hangul Text Layout and Typography 한국어 텍스트 레이아웃 및 타이포그래피를 위한 요구사항",
    "shortname": "klreq",
    "editor-draft": "http://w3c.github.io/klreq/",
    "_links": {
      "self": {
        "href": "https://api.w3.org/specifications/klreq"
      },
      "version-history": {
        "href": "https://api.w3.org/specifications/klreq/versions"
      },
      "first-version": {
        "href": "https://api.w3.org/specifications/klreq/versions/20130514",
        "title": "Working Draft"
      },
      "latest-version": {
        "href": "https://api.w3.org/specifications/klreq/versions/20150723",
        "title": "Working Draft"
      }
    },
    "editorsdraft": "http://w3c.github.io/klreq/",
    "versions": [
      {
        "status": "Working Draft",
        "rec-track": false,
        "editor-draft": "http://w3c.github.io/klreq/",
        "uri": "http://www.w3.org/TR/2015/WD-klreq-20150723/",
        "date": "2015-07-23",
        "informative": false,
        "title": "Requirements for Hangul Text Layout and Typography 한국어 텍스트 레이아웃 및 타이포그래피를 위한 요구사항",
        "shortlink": "http://www.w3.org/TR/klreq/",
        "process-rules": "http://www.w3.org/2014/Process-20140801/",
        "_links": {
          "self": {
            "href": "https://api.w3.org/specifications/klreq/versions/20150723"
          },
          "editors": {
            "href": "https://api.w3.org/specifications/klreq/versions/20150723/editors"
          },
          "deliverers": {
            "href": "https://api.w3.org/specifications/klreq/versions/20150723/deliverers"
          },
          "specification": {
            "href": "https://api.w3.org/specifications/klreq"
          },
          "predecessor-version": {
            "href": "https://api.w3.org/specifications/klreq/versions/20150723/predecessors"
          }
        }
      },
      {
        "status": "Working Draft",
        "rec-track": false,
        "editor-draft": "http://w3c.github.io/klreq/",
        "uri": "http://www.w3.org/TR/2015/WD-klreq-20150630/",
        "date": "2015-06-30",
        "informative": false,
        "title": "Requirements for Hangul Text Layout and Typography",
        "shortlink": "http://www.w3.org/TR/klreq/",
        "process-rules": "http://www.w3.org/2014/Process-20140801/",
        "_links": {
          "self": {
            "href": "https://api.w3.org/specifications/klreq/versions/20150630"
          },
          "editors": {
            "href": "https://api.w3.org/specifications/klreq/versions/20150630/editors"
          },
          "deliverers": {
            "href": "https://api.w3.org/specifications/klreq/versions/20150630/deliverers"
          },
          "specification": {
            "href": "https://api.w3.org/specifications/klreq"
          },
          "predecessor-version": {
            "href": "https://api.w3.org/specifications/klreq/versions/20150630/predecessors"
          },
          "successor-version": {
            "href": "https://api.w3.org/specifications/klreq/versions/20150630/successors"
          }
        }
      },
      {
        "status": "Working Draft",
        "rec-track": false,
        "editor-draft": "http://w3c.github.io/klreq/",
        "uri": "http://www.w3.org/TR/2015/WD-klreq-20150414/",
        "date": "2015-04-14",
        "informative": true,
        "title": "Requirements for Hangul Text Layout and Typography",
        "shortlink": "http://www.w3.org/TR/klreq/",
        "process-rules": "http://www.w3.org/2014/Process-20140801/",
        "_links": {
          "self": {
            "href": "https://api.w3.org/specifications/klreq/versions/20150414"
          },
          "editors": {
            "href": "https://api.w3.org/specifications/klreq/versions/20150414/editors"
          },
          "deliverers": {
            "href": "https://api.w3.org/specifications/klreq/versions/20150414/deliverers"
          },
          "specification": {
            "href": "https://api.w3.org/specifications/klreq"
          },
          "predecessor-version": {
            "href": "https://api.w3.org/specifications/klreq/versions/20150414/predecessors"
          },
          "successor-version": {
            "href": "https://api.w3.org/specifications/klreq/versions/20150414/successors"
          }
        }
      },
      {
        "status": "Working Draft",
        "rec-track": false,
        "editor-draft": "http://w3c.github.io/klreq/",
        "uri": "http://www.w3.org/TR/2013/WD-klreq-20130514/",
        "date": "2013-05-14",
        "informative": false,
        "title": "Requirements for Hangul Text Layout and Typography",
        "shortlink": "http://www.w3.org/TR/klreq/",
        "_links": {
          "self": {
            "href": "https://api.w3.org/specifications/klreq/versions/20130514"
          },
          "editors": {
            "href": "https://api.w3.org/specifications/klreq/versions/20130514/editors"
          },
          "deliverers": {
            "href": "https://api.w3.org/specifications/klreq/versions/20130514/deliverers"
          },
          "specification": {
            "href": "https://api.w3.org/specifications/klreq"
          },
          "successor-version": {
            "href": "https://api.w3.org/specifications/klreq/versions/20130514/successors"
          }
        }
      }
    ]
  },
  {
    "shortlink": "http://www.w3.org/TR/ltli/",
    "description": "<p> Describes mechanisms based on BCP 47 for identifying or selecting the language of content or locale preferences used to process information using Web technologies. </p>",
    "title": "Language Tags and Locale Identifiers for the World Wide Web",
    "shortname": "ltli",
    "editor-draft": "http://w3c.github.io/ltli/",
    "_links": {
      "self": {
        "href": "https://api.w3.org/specifications/ltli"
      },
      "version-history": {
        "href": "https://api.w3.org/specifications/ltli/versions"
      },
      "first-version": {
        "href": "https://api.w3.org/specifications/ltli/versions/20060419",
        "title": "Working Draft"
      },
      "latest-version": {
        "href": "https://api.w3.org/specifications/ltli/versions/20150423",
        "title": "Working Draft"
      }
    },
    "editorsdraft": "http://w3c.github.io/ltli/",
    "versions": [
      {
        "status": "Working Draft",
        "rec-track": false,
        "editor-draft": "http://w3c.github.io/ltli/",
        "uri": "http://www.w3.org/TR/2015/WD-ltli-20150423/",
        "date": "2015-04-23",
        "informative": true,
        "title": "Language Tags and Locale Identifiers for the World Wide Web",
        "shortlink": "http://www.w3.org/TR/ltli/",
        "process-rules": "http://www.w3.org/2014/Process-20140801/",
        "_links": {
          "self": {
            "href": "https://api.w3.org/specifications/ltli/versions/20150423"
          },
          "editors": {
            "href": "https://api.w3.org/specifications/ltli/versions/20150423/editors"
          },
          "deliverers": {
            "href": "https://api.w3.org/specifications/ltli/versions/20150423/deliverers"
          },
          "specification": {
            "href": "https://api.w3.org/specifications/ltli"
          },
          "predecessor-version": {
            "href": "https://api.w3.org/specifications/ltli/versions/20150423/predecessors"
          }
        }
      },
      {
        "status": "Working Draft",
        "rec-track": true,
        "editor-draft": "http://w3c.github.io/ltli/",
        "uri": "http://www.w3.org/TR/2006/WD-ltli-20060612/",
        "date": "2006-06-12",
        "informative": false,
        "title": "Language Tags and Locale Identifiers for the World Wide Web",
        "shortlink": "http://www.w3.org/TR/ltli/",
        "_links": {
          "self": {
            "href": "https://api.w3.org/specifications/ltli/versions/20060612"
          },
          "editors": {
            "href": "https://api.w3.org/specifications/ltli/versions/20060612/editors"
          },
          "deliverers": {
            "href": "https://api.w3.org/specifications/ltli/versions/20060612/deliverers"
          },
          "specification": {
            "href": "https://api.w3.org/specifications/ltli"
          },
          "predecessor-version": {
            "href": "https://api.w3.org/specifications/ltli/versions/20060612/predecessors"
          },
          "successor-version": {
            "href": "https://api.w3.org/specifications/ltli/versions/20060612/successors"
          }
        }
      },
      {
        "status": "Working Draft",
        "rec-track": true,
        "editor-draft": "http://w3c.github.io/ltli/",
        "uri": "http://www.w3.org/TR/2006/WD-ltli-20060419/",
        "date": "2006-04-19",
        "informative": false,
        "title": "Language Tags and Locale Identifiers for the World Wide Web",
        "shortlink": "http://www.w3.org/TR/ltli/",
        "_links": {
          "self": {
            "href": "https://api.w3.org/specifications/ltli/versions/20060419"
          },
          "editors": {
            "href": "https://api.w3.org/specifications/ltli/versions/20060419/editors"
          },
          "deliverers": {
            "href": "https://api.w3.org/specifications/ltli/versions/20060419/deliverers"
          },
          "specification": {
            "href": "https://api.w3.org/specifications/ltli"
          },
          "successor-version": {
            "href": "https://api.w3.org/specifications/ltli/versions/20060419/successors"
          }
        }
      }
    ]
  },
  {
    "shortlink": "https://www.w3.org/TR/typography/",
    "description": "<p>This document points browser implementers and specification developers to information about how to support typographic features of scripts or writing systems from around the world, and also points to relevant information in specifications, to tests, and to useful articles and papers. It is not exhaustive, and will be added to from time to time.</p>",
    "title": "International text layout and typography index",
    "shortname": "typography",
    "editor-draft": "https://w3c.github.io/typography/",
    "_links": {
      "self": {
        "href": "https://api.w3.org/specifications/typography"
      },
      "version-history": {
        "href": "https://api.w3.org/specifications/typography/versions"
      },
      "first-version": {
        "href": "https://api.w3.org/specifications/typography/versions/20170209",
        "title": "Working Draft"
      },
      "latest-version": {
        "href": "https://api.w3.org/specifications/typography/versions/20180828",
        "title": "Working Draft"
      }
    },
    "editorsdraft": "https://w3c.github.io/typography/",
    "versions": [
      {
        "status": "Working Draft",
        "rec-track": false,
        "editor-draft": "https://w3c.github.io/typography/",
        "uri": "https://www.w3.org/TR/2018/WD-typography-20180828/",
        "date": "2018-08-28",
        "informative": false,
        "title": "International text layout and typography index",
        "shortlink": "https://www.w3.org/TR/typography/",
        "process-rules": "https://www.w3.org/2018/Process-20180201/",
        "_links": {
          "self": {
            "href": "https://api.w3.org/specifications/typography/versions/20180828"
          },
          "editors": {
            "href": "https://api.w3.org/specifications/typography/versions/20180828/editors"
          },
          "deliverers": {
            "href": "https://api.w3.org/specifications/typography/versions/20180828/deliverers"
          },
          "specification": {
            "href": "https://api.w3.org/specifications/typography"
          },
          "predecessor-version": {
            "href": "https://api.w3.org/specifications/typography/versions/20180828/predecessors"
          }
        }
      },
      {
        "status": "Working Draft",
        "rec-track": false,
        "editor-draft": "https://w3c.github.io/typography/",
        "uri": "https://www.w3.org/TR/2017/WD-typography-20170209/",
        "date": "2017-02-09",
        "informative": false,
        "title": "International text layout and typography index",
        "shortlink": "https://www.w3.org/TR/typography/",
        "process-rules": "https://www.w3.org/2015/Process-20150901/",
        "_links": {
          "self": {
            "href": "https://api.w3.org/specifications/typography/versions/20170209"
          },
          "editors": {
            "href": "https://api.w3.org/specifications/typography/versions/20170209/editors"
          },
          "deliverers": {
            "href": "https://api.w3.org/specifications/typography/versions/20170209/deliverers"
          },
          "specification": {
            "href": "https://api.w3.org/specifications/typography"
          },
          "successor-version": {
            "href": "https://api.w3.org/specifications/typography/versions/20170209/successors"
          }
        }
      }
    ]
  }
]