{
  "https://www.w3.org/TR/shacl/": {
    "repo": {
      "owner": "w3c",
      "name": "data-shapes"
    },
    "issues": [
      {
        "state": "closed",
        "number": 45,
        "created_at": "2017-03-17T03:06:36Z",
        "closed_at": "2017-03-21T01:54:31Z",
        "title": "Intent to use SHACL",
        "labels": [
          {
            "id": 561769025,
            "url": "https://api.github.com/repos/w3c/data-shapes/labels/No%20Action%20Required",
            "name": "No Action Required",
            "color": "d4c5f9",
            "default": false
          }
        ],
        "assignee": null,
        "isPullRequest": false
      },
      {
        "state": "open",
        "number": 44,
        "created_at": "2017-03-16T17:39:21Z",
        "closed_at": null,
        "title": "Reference for BCP47",
        "labels": [
          {
            "id": 559868783,
            "url": "https://api.github.com/repos/w3c/data-shapes/labels/Commenter%20Timeout%20(assuming%20satisfied)",
            "name": "Commenter Timeout (assuming satisfied)",
            "color": "fef2c0",
            "default": false
          },
          {
            "id": 562399328,
            "url": "https://api.github.com/repos/w3c/data-shapes/labels/i18n-comment",
            "name": "i18n-comment",
            "color": "d4c5f9",
            "default": false
          }
        ],
        "assignee": null,
        "isPullRequest": false
      },
      {
        "state": "open",
        "number": 43,
        "created_at": "2017-03-16T17:37:44Z",
        "closed_at": null,
        "title": "String without the notion of a character",
        "labels": [
          {
            "id": 562399328,
            "url": "https://api.github.com/repos/w3c/data-shapes/labels/i18n-comment",
            "name": "i18n-comment",
            "color": "d4c5f9",
            "default": false
          },
          {
            "id": 559868787,
            "url": "https://api.github.com/repos/w3c/data-shapes/labels/Needs%20Group%20Input/Decision",
            "name": "Needs Group Input/Decision",
            "color": "0052cc",
            "default": false
          }
        ],
        "assignee": null,
        "isPullRequest": false
      },
      {
        "state": "open",
        "number": 42,
        "created_at": "2017-03-16T17:33:29Z",
        "closed_at": null,
        "title": "Define the terms language range and the matching approach",
        "labels": [
          {
            "id": 562399328,
            "url": "https://api.github.com/repos/w3c/data-shapes/labels/i18n-comment",
            "name": "i18n-comment",
            "color": "d4c5f9",
            "default": false
          }
        ],
        "assignee": null,
        "isPullRequest": false
      },
      {
        "state": "closed",
        "number": 41,
        "created_at": "2017-03-16T17:29:53Z",
        "closed_at": "2017-03-17T04:28:10Z",
        "title": "Handling of meaningful multiple values",
        "labels": [
          {
            "id": 562399328,
            "url": "https://api.github.com/repos/w3c/data-shapes/labels/i18n-comment",
            "name": "i18n-comment",
            "color": "d4c5f9",
            "default": false
          },
          {
            "id": 561769025,
            "url": "https://api.github.com/repos/w3c/data-shapes/labels/No%20Action%20Required",
            "name": "No Action Required",
            "color": "d4c5f9",
            "default": false
          }
        ],
        "assignee": null,
        "isPullRequest": false
      },
      {
        "state": "open",
        "number": 40,
        "created_at": "2017-03-16T17:26:35Z",
        "closed_at": null,
        "title": "Standardized way to add indications of text direction",
        "labels": [
          {
            "id": 562399328,
            "url": "https://api.github.com/repos/w3c/data-shapes/labels/i18n-comment",
            "name": "i18n-comment",
            "color": "d4c5f9",
            "default": false
          }
        ],
        "assignee": null,
        "isPullRequest": false
      },
      {
        "state": "closed",
        "number": 39,
        "created_at": "2017-03-16T17:21:32Z",
        "closed_at": "2017-03-17T04:16:21Z",
        "title": "RDF text strings & language",
        "labels": [
          {
            "id": 562399328,
            "url": "https://api.github.com/repos/w3c/data-shapes/labels/i18n-comment",
            "name": "i18n-comment",
            "color": "d4c5f9",
            "default": false
          },
          {
            "id": 561769025,
            "url": "https://api.github.com/repos/w3c/data-shapes/labels/No%20Action%20Required",
            "name": "No Action Required",
            "color": "d4c5f9",
            "default": false
          }
        ],
        "assignee": null,
        "isPullRequest": false
      },
      {
        "state": "closed",
        "number": 38,
        "created_at": "2017-03-16T01:15:14Z",
        "closed_at": "2017-03-16T03:15:35Z",
        "title": "SPARQL additions ",
        "labels": [
          {
            "id": 559868790,
            "url": "https://api.github.com/repos/w3c/data-shapes/labels/Commenter%20Satisfied",
            "name": "Commenter Satisfied",
            "color": "bfe5bf",
            "default": false
          },
          {
            "id": 559868791,
            "url": "https://api.github.com/repos/w3c/data-shapes/labels/Postponed%20(revisit%20in%20future%20effort)",
            "name": "Postponed (revisit in future effort)",
            "color": "cccccc",
            "default": false
          }
        ],
        "assignee": null,
        "isPullRequest": false
      },
      {
        "state": "closed",
        "number": 37,
        "created_at": "2017-03-14T22:47:40Z",
        "closed_at": "2017-03-14T23:02:09Z",
        "title": "ACTION-48 : some changes based on first review",
        "labels": [],
        "assignee": null,
        "isPullRequest": true
      },
      {
        "state": "open",
        "number": 36,
        "created_at": "2017-03-10T00:00:15Z",
        "closed_at": null,
        "title": "Ambiguity in examples",
        "labels": [
          {
            "id": 559868786,
            "url": "https://api.github.com/repos/w3c/data-shapes/labels/Editorial%20(would%20not%20change%20implementations)",
            "name": "Editorial (would not change implementations)",
            "color": "006b75",
            "default": false
          },
          {
            "id": 559868784,
            "url": "https://api.github.com/repos/w3c/data-shapes/labels/Waiting%20for%20Commenter",
            "name": "Waiting for Commenter",
            "color": "fbca04",
            "default": false
          }
        ],
        "assignee": null,
        "isPullRequest": false
      },
      {
        "state": "closed",
        "number": 35,
        "created_at": "2017-03-09T21:25:02Z",
        "closed_at": "2017-03-16T00:50:27Z",
        "title": "Inclusion of sh:phase and sh:Phase",
        "labels": [
          {
            "id": 559868790,
            "url": "https://api.github.com/repos/w3c/data-shapes/labels/Commenter%20Satisfied",
            "name": "Commenter Satisfied",
            "color": "bfe5bf",
            "default": false
          }
        ],
        "assignee": null,
        "isPullRequest": false
      },
      {
        "state": "closed",
        "number": 34,
        "created_at": "2017-03-09T15:37:01Z",
        "closed_at": "2017-03-21T01:54:31Z",
        "title": "Feedback : Shape Graphs Usage",
        "labels": [
          {
            "id": 561769025,
            "url": "https://api.github.com/repos/w3c/data-shapes/labels/No%20Action%20Required",
            "name": "No Action Required",
            "color": "d4c5f9",
            "default": false
          }
        ],
        "assignee": null,
        "isPullRequest": false
      },
      {
        "state": "closed",
        "number": 33,
        "created_at": "2017-03-09T14:54:07Z",
        "closed_at": "2017-03-21T01:54:31Z",
        "title": "Feedback: Evidence of interest in SHACL",
        "labels": [
          {
            "id": 561769025,
            "url": "https://api.github.com/repos/w3c/data-shapes/labels/No%20Action%20Required",
            "name": "No Action Required",
            "color": "d4c5f9",
            "default": false
          }
        ],
        "assignee": null,
        "isPullRequest": false
      },
      {
        "state": "open",
        "number": 32,
        "created_at": "2017-03-08T22:46:53Z",
        "closed_at": null,
        "title": "Problems editing SHACL with Protégé",
        "labels": [
          {
            "id": 559868787,
            "url": "https://api.github.com/repos/w3c/data-shapes/labels/Needs%20Group%20Input/Decision",
            "name": "Needs Group Input/Decision",
            "color": "0052cc",
            "default": false
          }
        ],
        "assignee": null,
        "isPullRequest": false
      },
      {
        "state": "closed",
        "number": 31,
        "created_at": "2017-03-07T09:31:21Z",
        "closed_at": "2017-03-07T22:31:06Z",
        "title": "rdf:List typo fix",
        "labels": [],
        "assignee": null,
        "isPullRequest": true
      },
      {
        "state": "closed",
        "number": 30,
        "created_at": "2017-03-07T09:25:26Z",
        "closed_at": "2017-03-07T22:35:15Z",
        "title": "ACTION-48: Produce a json-ld @context draft",
        "labels": [],
        "assignee": null,
        "isPullRequest": true
      },
      {
        "state": "closed",
        "number": 29,
        "created_at": "2017-03-07T01:27:36Z",
        "closed_at": "2017-03-07T22:00:21Z",
        "title": "sh:query non-normative?",
        "labels": [
          {
            "id": 559868790,
            "url": "https://api.github.com/repos/w3c/data-shapes/labels/Commenter%20Satisfied",
            "name": "Commenter Satisfied",
            "color": "bfe5bf",
            "default": false
          }
        ],
        "assignee": null,
        "isPullRequest": false
      },
      {
        "state": "closed",
        "number": 28,
        "created_at": "2017-03-06T10:54:02Z",
        "closed_at": "2017-03-06T22:58:20Z",
        "title": "Wrong predicate in sh:disjoint description",
        "labels": [
          {
            "id": 559868783,
            "url": "https://api.github.com/repos/w3c/data-shapes/labels/Commenter%20Timeout%20(assuming%20satisfied)",
            "name": "Commenter Timeout (assuming satisfied)",
            "color": "fef2c0",
            "default": false
          }
        ],
        "assignee": null,
        "isPullRequest": false
      },
      {
        "state": "closed",
        "number": 27,
        "created_at": "2017-03-03T20:42:41Z",
        "closed_at": "2017-03-21T01:54:31Z",
        "title": "Plans to use and implement",
        "labels": [
          {
            "id": 561769025,
            "url": "https://api.github.com/repos/w3c/data-shapes/labels/No%20Action%20Required",
            "name": "No Action Required",
            "color": "d4c5f9",
            "default": false
          }
        ],
        "assignee": null,
        "isPullRequest": false
      },
      {
        "state": "closed",
        "number": 26,
        "created_at": "2017-02-08T06:45:27Z",
        "closed_at": "2017-03-21T04:36:36Z",
        "title": "References not rendering (Firefox 51.0.1)",
        "labels": [
          {
            "id": 559868786,
            "url": "https://api.github.com/repos/w3c/data-shapes/labels/Editorial%20(would%20not%20change%20implementations)",
            "name": "Editorial (would not change implementations)",
            "color": "006b75",
            "default": false
          }
        ],
        "assignee": null,
        "isPullRequest": false
      },
      {
        "state": "closed",
        "number": 25,
        "created_at": "2016-12-21T17:42:28Z",
        "closed_at": "2017-03-03T05:55:34Z",
        "title": "Re 4.2.3 sh:nodeKind: add a notice about putting a constraint on nodes to be blank nodes",
        "labels": [
          {
            "id": 559868783,
            "url": "https://api.github.com/repos/w3c/data-shapes/labels/Commenter%20Timeout%20(assuming%20satisfied)",
            "name": "Commenter Timeout (assuming satisfied)",
            "color": "fef2c0",
            "default": false
          }
        ],
        "assignee": null,
        "isPullRequest": false
      },
      {
        "state": "closed",
        "number": 24,
        "created_at": "2016-12-21T16:50:43Z",
        "closed_at": "2017-03-03T05:55:49Z",
        "title": "Re 4.2.3 sh:nodeKind: provide an instance for the combination of all kinds",
        "labels": [
          {
            "id": 559868783,
            "url": "https://api.github.com/repos/w3c/data-shapes/labels/Commenter%20Timeout%20(assuming%20satisfied)",
            "name": "Commenter Timeout (assuming satisfied)",
            "color": "fef2c0",
            "default": false
          }
        ],
        "assignee": null,
        "isPullRequest": false
      },
      {
        "state": "closed",
        "number": 23,
        "created_at": "2016-11-09T15:44:26Z",
        "closed_at": "2017-03-16T00:32:47Z",
        "title": "validation filter ordering",
        "labels": [],
        "assignee": null,
        "isPullRequest": true
      },
      {
        "state": "closed",
        "number": 22,
        "created_at": "2016-10-30T08:14:56Z",
        "closed_at": "2017-03-16T00:34:55Z",
        "title": "examples use tabular summary",
        "labels": [],
        "assignee": null,
        "isPullRequest": true
      },
      {
        "state": "closed",
        "number": 21,
        "created_at": "2016-09-07T10:04:06Z",
        "closed_at": "2016-09-07T20:58:45Z",
        "title": "typo",
        "labels": [],
        "assignee": null,
        "isPullRequest": true
      },
      {
        "state": "closed",
        "number": 20,
        "created_at": "2016-09-07T09:29:04Z",
        "closed_at": "2016-09-07T20:48:29Z",
        "title": "typo",
        "labels": [],
        "assignee": null,
        "isPullRequest": true
      },
      {
        "state": "closed",
        "number": 19,
        "created_at": "2016-09-07T09:25:56Z",
        "closed_at": "2016-09-07T20:47:48Z",
        "title": "typo",
        "labels": [],
        "assignee": null,
        "isPullRequest": true
      },
      {
        "state": "closed",
        "number": 18,
        "created_at": "2016-04-23T20:36:24Z",
        "closed_at": "2016-04-27T15:05:27Z",
        "title": "Update index.html",
        "labels": [],
        "assignee": null,
        "isPullRequest": true
      },
      {
        "state": "closed",
        "number": 17,
        "created_at": "2016-04-21T20:07:30Z",
        "closed_at": "2016-04-23T13:57:56Z",
        "title": "Update index.html",
        "labels": [],
        "assignee": null,
        "isPullRequest": true
      },
      {
        "state": "closed",
        "number": 16,
        "created_at": "2016-04-20T00:03:03Z",
        "closed_at": "2016-04-20T06:41:54Z",
        "title": "Update index.html",
        "labels": [],
        "assignee": null,
        "isPullRequest": true
      },
      {
        "state": "closed",
        "number": 15,
        "created_at": "2016-02-11T03:27:40Z",
        "closed_at": "2016-02-11T03:27:48Z",
        "title": "ISSUE 92 partition constraint",
        "labels": [],
        "assignee": null,
        "isPullRequest": true
      },
      {
        "state": "closed",
        "number": 14,
        "created_at": "2016-01-22T02:43:01Z",
        "closed_at": "2016-01-22T02:47:04Z",
        "title": "updated definition for ISSUE-23",
        "labels": [],
        "assignee": null,
        "isPullRequest": true
      },
      {
        "state": "closed",
        "number": 13,
        "created_at": "2016-01-19T19:28:56Z",
        "closed_at": "2016-01-19T19:29:04Z",
        "title": "Implemented proposal for ISSUE-23",
        "labels": [],
        "assignee": null,
        "isPullRequest": true
      },
      {
        "state": "closed",
        "number": 12,
        "created_at": "2016-01-19T00:10:39Z",
        "closed_at": "2016-01-19T00:10:50Z",
        "title": "Implemented resolution on recursive shapes, ISSUE-22",
        "labels": [],
        "assignee": null,
        "isPullRequest": true
      },
      {
        "state": "closed",
        "number": 11,
        "created_at": "2016-01-18T23:38:39Z",
        "closed_at": "2016-01-18T23:38:51Z",
        "title": "Implemented resolution of ISSUE-49",
        "labels": [],
        "assignee": null,
        "isPullRequest": true
      },
      {
        "state": "closed",
        "number": 10,
        "created_at": "2015-12-16T12:02:01Z",
        "closed_at": "2015-12-16T12:02:17Z",
        "title": "Wrote shacl-vocab.ttl and generated HTML",
        "labels": [],
        "assignee": null,
        "isPullRequest": true
      },
      {
        "state": "closed",
        "number": 9,
        "created_at": "2015-12-01T14:06:24Z",
        "closed_at": "2015-12-02T20:58:22Z",
        "title": "minor mistake in spec - ex:unsinged",
        "labels": [
          {
            "id": 559868790,
            "url": "https://api.github.com/repos/w3c/data-shapes/labels/Commenter%20Satisfied",
            "name": "Commenter Satisfied",
            "color": "bfe5bf",
            "default": false
          }
        ],
        "assignee": null,
        "isPullRequest": false
      },
      {
        "state": "closed",
        "number": 8,
        "created_at": "2015-10-28T22:38:39Z",
        "closed_at": "2015-10-28T22:39:05Z",
        "title": "Separated definitions of sh:qualifiedMinCount and sh:qualifiedMaxCount",
        "labels": [],
        "assignee": null,
        "isPullRequest": true
      },
      {
        "state": "closed",
        "number": 7,
        "created_at": "2015-10-22T21:15:14Z",
        "closed_at": "2015-10-22T21:15:39Z",
        "title": "Define sh:minLength, sh:maxLength, sh:qualifiedMinCount, and sh:qualifiedMaxCount without reference to default values",
        "labels": [],
        "assignee": null,
        "isPullRequest": true
      },
      {
        "state": "closed",
        "number": 6,
        "created_at": "2015-10-15T16:30:50Z",
        "closed_at": "2015-10-15T16:31:42Z",
        "title": "Defined sh:minCount and sh:maxCount without mention of default values",
        "labels": [],
        "assignee": null,
        "isPullRequest": true
      },
      {
        "state": "closed",
        "number": 5,
        "created_at": "2015-10-15T15:44:26Z",
        "closed_at": "2015-10-15T15:46:17Z",
        "title": "Updated examples 3,4,5",
        "labels": [],
        "assignee": null,
        "isPullRequest": true
      },
      {
        "state": "closed",
        "number": 4,
        "created_at": "2015-08-14T11:15:25Z",
        "closed_at": "2017-03-03T05:54:36Z",
        "title": "Page not found for ldom.ttl",
        "labels": [
          {
            "id": 559868783,
            "url": "https://api.github.com/repos/w3c/data-shapes/labels/Commenter%20Timeout%20(assuming%20satisfied)",
            "name": "Commenter Timeout (assuming satisfied)",
            "color": "fef2c0",
            "default": false
          }
        ],
        "assignee": null,
        "isPullRequest": false
      },
      {
        "state": "closed",
        "number": 3,
        "created_at": "2015-06-04T06:31:56Z",
        "closed_at": "2017-03-03T05:54:57Z",
        "title": "what about reification?",
        "labels": [
          {
            "id": 559868783,
            "url": "https://api.github.com/repos/w3c/data-shapes/labels/Commenter%20Timeout%20(assuming%20satisfied)",
            "name": "Commenter Timeout (assuming satisfied)",
            "color": "fef2c0",
            "default": false
          }
        ],
        "assignee": null,
        "isPullRequest": false
      },
      {
        "state": "closed",
        "number": 2,
        "created_at": "2015-05-02T15:45:54Z",
        "closed_at": "2015-05-02T21:26:22Z",
        "title": "Fix typo",
        "labels": [],
        "assignee": null,
        "isPullRequest": true
      },
      {
        "state": "closed",
        "number": 1,
        "created_at": "2015-04-29T14:48:15Z",
        "closed_at": "2015-12-16T12:22:10Z",
        "title": "minor mistake in specification",
        "labels": [
          {
            "id": 559868783,
            "url": "https://api.github.com/repos/w3c/data-shapes/labels/Commenter%20Timeout%20(assuming%20satisfied)",
            "name": "Commenter Timeout (assuming satisfied)",
            "color": "fef2c0",
            "default": false
          }
        ],
        "assignee": null,
        "isPullRequest": false
      }
    ]
  },
  "https://www.w3.org/TR/shacl-abstract-syntax/": {
    "repo": {
      "owner": "w3c",
      "name": "data-shapes"
    },
    "issues": [
      {
        "state": "closed",
        "number": 45,
        "created_at": "2017-03-17T03:06:36Z",
        "closed_at": "2017-03-21T01:54:31Z",
        "title": "Intent to use SHACL",
        "labels": [
          {
            "id": 561769025,
            "url": "https://api.github.com/repos/w3c/data-shapes/labels/No%20Action%20Required",
            "name": "No Action Required",
            "color": "d4c5f9",
            "default": false
          }
        ],
        "assignee": null,
        "isPullRequest": false
      },
      {
        "state": "open",
        "number": 44,
        "created_at": "2017-03-16T17:39:21Z",
        "closed_at": null,
        "title": "Reference for BCP47",
        "labels": [
          {
            "id": 559868783,
            "url": "https://api.github.com/repos/w3c/data-shapes/labels/Commenter%20Timeout%20(assuming%20satisfied)",
            "name": "Commenter Timeout (assuming satisfied)",
            "color": "fef2c0",
            "default": false
          },
          {
            "id": 562399328,
            "url": "https://api.github.com/repos/w3c/data-shapes/labels/i18n-comment",
            "name": "i18n-comment",
            "color": "d4c5f9",
            "default": false
          }
        ],
        "assignee": null,
        "isPullRequest": false
      },
      {
        "state": "open",
        "number": 43,
        "created_at": "2017-03-16T17:37:44Z",
        "closed_at": null,
        "title": "String without the notion of a character",
        "labels": [
          {
            "id": 562399328,
            "url": "https://api.github.com/repos/w3c/data-shapes/labels/i18n-comment",
            "name": "i18n-comment",
            "color": "d4c5f9",
            "default": false
          },
          {
            "id": 559868787,
            "url": "https://api.github.com/repos/w3c/data-shapes/labels/Needs%20Group%20Input/Decision",
            "name": "Needs Group Input/Decision",
            "color": "0052cc",
            "default": false
          }
        ],
        "assignee": null,
        "isPullRequest": false
      },
      {
        "state": "open",
        "number": 42,
        "created_at": "2017-03-16T17:33:29Z",
        "closed_at": null,
        "title": "Define the terms language range and the matching approach",
        "labels": [
          {
            "id": 562399328,
            "url": "https://api.github.com/repos/w3c/data-shapes/labels/i18n-comment",
            "name": "i18n-comment",
            "color": "d4c5f9",
            "default": false
          }
        ],
        "assignee": null,
        "isPullRequest": false
      },
      {
        "state": "closed",
        "number": 41,
        "created_at": "2017-03-16T17:29:53Z",
        "closed_at": "2017-03-17T04:28:10Z",
        "title": "Handling of meaningful multiple values",
        "labels": [
          {
            "id": 562399328,
            "url": "https://api.github.com/repos/w3c/data-shapes/labels/i18n-comment",
            "name": "i18n-comment",
            "color": "d4c5f9",
            "default": false
          },
          {
            "id": 561769025,
            "url": "https://api.github.com/repos/w3c/data-shapes/labels/No%20Action%20Required",
            "name": "No Action Required",
            "color": "d4c5f9",
            "default": false
          }
        ],
        "assignee": null,
        "isPullRequest": false
      },
      {
        "state": "open",
        "number": 40,
        "created_at": "2017-03-16T17:26:35Z",
        "closed_at": null,
        "title": "Standardized way to add indications of text direction",
        "labels": [
          {
            "id": 562399328,
            "url": "https://api.github.com/repos/w3c/data-shapes/labels/i18n-comment",
            "name": "i18n-comment",
            "color": "d4c5f9",
            "default": false
          }
        ],
        "assignee": null,
        "isPullRequest": false
      },
      {
        "state": "closed",
        "number": 39,
        "created_at": "2017-03-16T17:21:32Z",
        "closed_at": "2017-03-17T04:16:21Z",
        "title": "RDF text strings & language",
        "labels": [
          {
            "id": 562399328,
            "url": "https://api.github.com/repos/w3c/data-shapes/labels/i18n-comment",
            "name": "i18n-comment",
            "color": "d4c5f9",
            "default": false
          },
          {
            "id": 561769025,
            "url": "https://api.github.com/repos/w3c/data-shapes/labels/No%20Action%20Required",
            "name": "No Action Required",
            "color": "d4c5f9",
            "default": false
          }
        ],
        "assignee": null,
        "isPullRequest": false
      },
      {
        "state": "closed",
        "number": 38,
        "created_at": "2017-03-16T01:15:14Z",
        "closed_at": "2017-03-16T03:15:35Z",
        "title": "SPARQL additions ",
        "labels": [
          {
            "id": 559868790,
            "url": "https://api.github.com/repos/w3c/data-shapes/labels/Commenter%20Satisfied",
            "name": "Commenter Satisfied",
            "color": "bfe5bf",
            "default": false
          },
          {
            "id": 559868791,
            "url": "https://api.github.com/repos/w3c/data-shapes/labels/Postponed%20(revisit%20in%20future%20effort)",
            "name": "Postponed (revisit in future effort)",
            "color": "cccccc",
            "default": false
          }
        ],
        "assignee": null,
        "isPullRequest": false
      },
      {
        "state": "closed",
        "number": 37,
        "created_at": "2017-03-14T22:47:40Z",
        "closed_at": "2017-03-14T23:02:09Z",
        "title": "ACTION-48 : some changes based on first review",
        "labels": [],
        "assignee": null,
        "isPullRequest": true
      },
      {
        "state": "open",
        "number": 36,
        "created_at": "2017-03-10T00:00:15Z",
        "closed_at": null,
        "title": "Ambiguity in examples",
        "labels": [
          {
            "id": 559868786,
            "url": "https://api.github.com/repos/w3c/data-shapes/labels/Editorial%20(would%20not%20change%20implementations)",
            "name": "Editorial (would not change implementations)",
            "color": "006b75",
            "default": false
          },
          {
            "id": 559868784,
            "url": "https://api.github.com/repos/w3c/data-shapes/labels/Waiting%20for%20Commenter",
            "name": "Waiting for Commenter",
            "color": "fbca04",
            "default": false
          }
        ],
        "assignee": null,
        "isPullRequest": false
      },
      {
        "state": "closed",
        "number": 35,
        "created_at": "2017-03-09T21:25:02Z",
        "closed_at": "2017-03-16T00:50:27Z",
        "title": "Inclusion of sh:phase and sh:Phase",
        "labels": [
          {
            "id": 559868790,
            "url": "https://api.github.com/repos/w3c/data-shapes/labels/Commenter%20Satisfied",
            "name": "Commenter Satisfied",
            "color": "bfe5bf",
            "default": false
          }
        ],
        "assignee": null,
        "isPullRequest": false
      },
      {
        "state": "closed",
        "number": 34,
        "created_at": "2017-03-09T15:37:01Z",
        "closed_at": "2017-03-21T01:54:31Z",
        "title": "Feedback : Shape Graphs Usage",
        "labels": [
          {
            "id": 561769025,
            "url": "https://api.github.com/repos/w3c/data-shapes/labels/No%20Action%20Required",
            "name": "No Action Required",
            "color": "d4c5f9",
            "default": false
          }
        ],
        "assignee": null,
        "isPullRequest": false
      },
      {
        "state": "closed",
        "number": 33,
        "created_at": "2017-03-09T14:54:07Z",
        "closed_at": "2017-03-21T01:54:31Z",
        "title": "Feedback: Evidence of interest in SHACL",
        "labels": [
          {
            "id": 561769025,
            "url": "https://api.github.com/repos/w3c/data-shapes/labels/No%20Action%20Required",
            "name": "No Action Required",
            "color": "d4c5f9",
            "default": false
          }
        ],
        "assignee": null,
        "isPullRequest": false
      },
      {
        "state": "open",
        "number": 32,
        "created_at": "2017-03-08T22:46:53Z",
        "closed_at": null,
        "title": "Problems editing SHACL with Protégé",
        "labels": [
          {
            "id": 559868787,
            "url": "https://api.github.com/repos/w3c/data-shapes/labels/Needs%20Group%20Input/Decision",
            "name": "Needs Group Input/Decision",
            "color": "0052cc",
            "default": false
          }
        ],
        "assignee": null,
        "isPullRequest": false
      },
      {
        "state": "closed",
        "number": 31,
        "created_at": "2017-03-07T09:31:21Z",
        "closed_at": "2017-03-07T22:31:06Z",
        "title": "rdf:List typo fix",
        "labels": [],
        "assignee": null,
        "isPullRequest": true
      },
      {
        "state": "closed",
        "number": 30,
        "created_at": "2017-03-07T09:25:26Z",
        "closed_at": "2017-03-07T22:35:15Z",
        "title": "ACTION-48: Produce a json-ld @context draft",
        "labels": [],
        "assignee": null,
        "isPullRequest": true
      },
      {
        "state": "closed",
        "number": 29,
        "created_at": "2017-03-07T01:27:36Z",
        "closed_at": "2017-03-07T22:00:21Z",
        "title": "sh:query non-normative?",
        "labels": [
          {
            "id": 559868790,
            "url": "https://api.github.com/repos/w3c/data-shapes/labels/Commenter%20Satisfied",
            "name": "Commenter Satisfied",
            "color": "bfe5bf",
            "default": false
          }
        ],
        "assignee": null,
        "isPullRequest": false
      },
      {
        "state": "closed",
        "number": 28,
        "created_at": "2017-03-06T10:54:02Z",
        "closed_at": "2017-03-06T22:58:20Z",
        "title": "Wrong predicate in sh:disjoint description",
        "labels": [
          {
            "id": 559868783,
            "url": "https://api.github.com/repos/w3c/data-shapes/labels/Commenter%20Timeout%20(assuming%20satisfied)",
            "name": "Commenter Timeout (assuming satisfied)",
            "color": "fef2c0",
            "default": false
          }
        ],
        "assignee": null,
        "isPullRequest": false
      },
      {
        "state": "closed",
        "number": 27,
        "created_at": "2017-03-03T20:42:41Z",
        "closed_at": "2017-03-21T01:54:31Z",
        "title": "Plans to use and implement",
        "labels": [
          {
            "id": 561769025,
            "url": "https://api.github.com/repos/w3c/data-shapes/labels/No%20Action%20Required",
            "name": "No Action Required",
            "color": "d4c5f9",
            "default": false
          }
        ],
        "assignee": null,
        "isPullRequest": false
      },
      {
        "state": "closed",
        "number": 26,
        "created_at": "2017-02-08T06:45:27Z",
        "closed_at": "2017-03-21T04:36:36Z",
        "title": "References not rendering (Firefox 51.0.1)",
        "labels": [
          {
            "id": 559868786,
            "url": "https://api.github.com/repos/w3c/data-shapes/labels/Editorial%20(would%20not%20change%20implementations)",
            "name": "Editorial (would not change implementations)",
            "color": "006b75",
            "default": false
          }
        ],
        "assignee": null,
        "isPullRequest": false
      },
      {
        "state": "closed",
        "number": 25,
        "created_at": "2016-12-21T17:42:28Z",
        "closed_at": "2017-03-03T05:55:34Z",
        "title": "Re 4.2.3 sh:nodeKind: add a notice about putting a constraint on nodes to be blank nodes",
        "labels": [
          {
            "id": 559868783,
            "url": "https://api.github.com/repos/w3c/data-shapes/labels/Commenter%20Timeout%20(assuming%20satisfied)",
            "name": "Commenter Timeout (assuming satisfied)",
            "color": "fef2c0",
            "default": false
          }
        ],
        "assignee": null,
        "isPullRequest": false
      },
      {
        "state": "closed",
        "number": 24,
        "created_at": "2016-12-21T16:50:43Z",
        "closed_at": "2017-03-03T05:55:49Z",
        "title": "Re 4.2.3 sh:nodeKind: provide an instance for the combination of all kinds",
        "labels": [
          {
            "id": 559868783,
            "url": "https://api.github.com/repos/w3c/data-shapes/labels/Commenter%20Timeout%20(assuming%20satisfied)",
            "name": "Commenter Timeout (assuming satisfied)",
            "color": "fef2c0",
            "default": false
          }
        ],
        "assignee": null,
        "isPullRequest": false
      },
      {
        "state": "closed",
        "number": 23,
        "created_at": "2016-11-09T15:44:26Z",
        "closed_at": "2017-03-16T00:32:47Z",
        "title": "validation filter ordering",
        "labels": [],
        "assignee": null,
        "isPullRequest": true
      },
      {
        "state": "closed",
        "number": 22,
        "created_at": "2016-10-30T08:14:56Z",
        "closed_at": "2017-03-16T00:34:55Z",
        "title": "examples use tabular summary",
        "labels": [],
        "assignee": null,
        "isPullRequest": true
      },
      {
        "state": "closed",
        "number": 21,
        "created_at": "2016-09-07T10:04:06Z",
        "closed_at": "2016-09-07T20:58:45Z",
        "title": "typo",
        "labels": [],
        "assignee": null,
        "isPullRequest": true
      },
      {
        "state": "closed",
        "number": 20,
        "created_at": "2016-09-07T09:29:04Z",
        "closed_at": "2016-09-07T20:48:29Z",
        "title": "typo",
        "labels": [],
        "assignee": null,
        "isPullRequest": true
      },
      {
        "state": "closed",
        "number": 19,
        "created_at": "2016-09-07T09:25:56Z",
        "closed_at": "2016-09-07T20:47:48Z",
        "title": "typo",
        "labels": [],
        "assignee": null,
        "isPullRequest": true
      },
      {
        "state": "closed",
        "number": 18,
        "created_at": "2016-04-23T20:36:24Z",
        "closed_at": "2016-04-27T15:05:27Z",
        "title": "Update index.html",
        "labels": [],
        "assignee": null,
        "isPullRequest": true
      },
      {
        "state": "closed",
        "number": 17,
        "created_at": "2016-04-21T20:07:30Z",
        "closed_at": "2016-04-23T13:57:56Z",
        "title": "Update index.html",
        "labels": [],
        "assignee": null,
        "isPullRequest": true
      },
      {
        "state": "closed",
        "number": 16,
        "created_at": "2016-04-20T00:03:03Z",
        "closed_at": "2016-04-20T06:41:54Z",
        "title": "Update index.html",
        "labels": [],
        "assignee": null,
        "isPullRequest": true
      },
      {
        "state": "closed",
        "number": 15,
        "created_at": "2016-02-11T03:27:40Z",
        "closed_at": "2016-02-11T03:27:48Z",
        "title": "ISSUE 92 partition constraint",
        "labels": [],
        "assignee": null,
        "isPullRequest": true
      },
      {
        "state": "closed",
        "number": 14,
        "created_at": "2016-01-22T02:43:01Z",
        "closed_at": "2016-01-22T02:47:04Z",
        "title": "updated definition for ISSUE-23",
        "labels": [],
        "assignee": null,
        "isPullRequest": true
      },
      {
        "state": "closed",
        "number": 13,
        "created_at": "2016-01-19T19:28:56Z",
        "closed_at": "2016-01-19T19:29:04Z",
        "title": "Implemented proposal for ISSUE-23",
        "labels": [],
        "assignee": null,
        "isPullRequest": true
      },
      {
        "state": "closed",
        "number": 12,
        "created_at": "2016-01-19T00:10:39Z",
        "closed_at": "2016-01-19T00:10:50Z",
        "title": "Implemented resolution on recursive shapes, ISSUE-22",
        "labels": [],
        "assignee": null,
        "isPullRequest": true
      },
      {
        "state": "closed",
        "number": 11,
        "created_at": "2016-01-18T23:38:39Z",
        "closed_at": "2016-01-18T23:38:51Z",
        "title": "Implemented resolution of ISSUE-49",
        "labels": [],
        "assignee": null,
        "isPullRequest": true
      },
      {
        "state": "closed",
        "number": 10,
        "created_at": "2015-12-16T12:02:01Z",
        "closed_at": "2015-12-16T12:02:17Z",
        "title": "Wrote shacl-vocab.ttl and generated HTML",
        "labels": [],
        "assignee": null,
        "isPullRequest": true
      },
      {
        "state": "closed",
        "number": 9,
        "created_at": "2015-12-01T14:06:24Z",
        "closed_at": "2015-12-02T20:58:22Z",
        "title": "minor mistake in spec - ex:unsinged",
        "labels": [
          {
            "id": 559868790,
            "url": "https://api.github.com/repos/w3c/data-shapes/labels/Commenter%20Satisfied",
            "name": "Commenter Satisfied",
            "color": "bfe5bf",
            "default": false
          }
        ],
        "assignee": null,
        "isPullRequest": false
      },
      {
        "state": "closed",
        "number": 8,
        "created_at": "2015-10-28T22:38:39Z",
        "closed_at": "2015-10-28T22:39:05Z",
        "title": "Separated definitions of sh:qualifiedMinCount and sh:qualifiedMaxCount",
        "labels": [],
        "assignee": null,
        "isPullRequest": true
      },
      {
        "state": "closed",
        "number": 7,
        "created_at": "2015-10-22T21:15:14Z",
        "closed_at": "2015-10-22T21:15:39Z",
        "title": "Define sh:minLength, sh:maxLength, sh:qualifiedMinCount, and sh:qualifiedMaxCount without reference to default values",
        "labels": [],
        "assignee": null,
        "isPullRequest": true
      },
      {
        "state": "closed",
        "number": 6,
        "created_at": "2015-10-15T16:30:50Z",
        "closed_at": "2015-10-15T16:31:42Z",
        "title": "Defined sh:minCount and sh:maxCount without mention of default values",
        "labels": [],
        "assignee": null,
        "isPullRequest": true
      },
      {
        "state": "closed",
        "number": 5,
        "created_at": "2015-10-15T15:44:26Z",
        "closed_at": "2015-10-15T15:46:17Z",
        "title": "Updated examples 3,4,5",
        "labels": [],
        "assignee": null,
        "isPullRequest": true
      },
      {
        "state": "closed",
        "number": 4,
        "created_at": "2015-08-14T11:15:25Z",
        "closed_at": "2017-03-03T05:54:36Z",
        "title": "Page not found for ldom.ttl",
        "labels": [
          {
            "id": 559868783,
            "url": "https://api.github.com/repos/w3c/data-shapes/labels/Commenter%20Timeout%20(assuming%20satisfied)",
            "name": "Commenter Timeout (assuming satisfied)",
            "color": "fef2c0",
            "default": false
          }
        ],
        "assignee": null,
        "isPullRequest": false
      },
      {
        "state": "closed",
        "number": 3,
        "created_at": "2015-06-04T06:31:56Z",
        "closed_at": "2017-03-03T05:54:57Z",
        "title": "what about reification?",
        "labels": [
          {
            "id": 559868783,
            "url": "https://api.github.com/repos/w3c/data-shapes/labels/Commenter%20Timeout%20(assuming%20satisfied)",
            "name": "Commenter Timeout (assuming satisfied)",
            "color": "fef2c0",
            "default": false
          }
        ],
        "assignee": null,
        "isPullRequest": false
      },
      {
        "state": "closed",
        "number": 2,
        "created_at": "2015-05-02T15:45:54Z",
        "closed_at": "2015-05-02T21:26:22Z",
        "title": "Fix typo",
        "labels": [],
        "assignee": null,
        "isPullRequest": true
      },
      {
        "state": "closed",
        "number": 1,
        "created_at": "2015-04-29T14:48:15Z",
        "closed_at": "2015-12-16T12:22:10Z",
        "title": "minor mistake in specification",
        "labels": [
          {
            "id": 559868783,
            "url": "https://api.github.com/repos/w3c/data-shapes/labels/Commenter%20Timeout%20(assuming%20satisfied)",
            "name": "Commenter Timeout (assuming satisfied)",
            "color": "fef2c0",
            "default": false
          }
        ],
        "assignee": null,
        "isPullRequest": false
      }
    ]
  },
  "http://www.w3.org/TR/shacl-ucr/": {
    "repo": {
      "owner": "w3c",
      "name": "data-shapes"
    },
    "issues": [
      {
        "state": "closed",
        "number": 45,
        "created_at": "2017-03-17T03:06:36Z",
        "closed_at": "2017-03-21T01:54:31Z",
        "title": "Intent to use SHACL",
        "labels": [
          {
            "id": 561769025,
            "url": "https://api.github.com/repos/w3c/data-shapes/labels/No%20Action%20Required",
            "name": "No Action Required",
            "color": "d4c5f9",
            "default": false
          }
        ],
        "assignee": null,
        "isPullRequest": false
      },
      {
        "state": "open",
        "number": 44,
        "created_at": "2017-03-16T17:39:21Z",
        "closed_at": null,
        "title": "Reference for BCP47",
        "labels": [
          {
            "id": 559868783,
            "url": "https://api.github.com/repos/w3c/data-shapes/labels/Commenter%20Timeout%20(assuming%20satisfied)",
            "name": "Commenter Timeout (assuming satisfied)",
            "color": "fef2c0",
            "default": false
          },
          {
            "id": 562399328,
            "url": "https://api.github.com/repos/w3c/data-shapes/labels/i18n-comment",
            "name": "i18n-comment",
            "color": "d4c5f9",
            "default": false
          }
        ],
        "assignee": null,
        "isPullRequest": false
      },
      {
        "state": "open",
        "number": 43,
        "created_at": "2017-03-16T17:37:44Z",
        "closed_at": null,
        "title": "String without the notion of a character",
        "labels": [
          {
            "id": 562399328,
            "url": "https://api.github.com/repos/w3c/data-shapes/labels/i18n-comment",
            "name": "i18n-comment",
            "color": "d4c5f9",
            "default": false
          },
          {
            "id": 559868787,
            "url": "https://api.github.com/repos/w3c/data-shapes/labels/Needs%20Group%20Input/Decision",
            "name": "Needs Group Input/Decision",
            "color": "0052cc",
            "default": false
          }
        ],
        "assignee": null,
        "isPullRequest": false
      },
      {
        "state": "open",
        "number": 42,
        "created_at": "2017-03-16T17:33:29Z",
        "closed_at": null,
        "title": "Define the terms language range and the matching approach",
        "labels": [
          {
            "id": 562399328,
            "url": "https://api.github.com/repos/w3c/data-shapes/labels/i18n-comment",
            "name": "i18n-comment",
            "color": "d4c5f9",
            "default": false
          }
        ],
        "assignee": null,
        "isPullRequest": false
      },
      {
        "state": "closed",
        "number": 41,
        "created_at": "2017-03-16T17:29:53Z",
        "closed_at": "2017-03-17T04:28:10Z",
        "title": "Handling of meaningful multiple values",
        "labels": [
          {
            "id": 562399328,
            "url": "https://api.github.com/repos/w3c/data-shapes/labels/i18n-comment",
            "name": "i18n-comment",
            "color": "d4c5f9",
            "default": false
          },
          {
            "id": 561769025,
            "url": "https://api.github.com/repos/w3c/data-shapes/labels/No%20Action%20Required",
            "name": "No Action Required",
            "color": "d4c5f9",
            "default": false
          }
        ],
        "assignee": null,
        "isPullRequest": false
      },
      {
        "state": "open",
        "number": 40,
        "created_at": "2017-03-16T17:26:35Z",
        "closed_at": null,
        "title": "Standardized way to add indications of text direction",
        "labels": [
          {
            "id": 562399328,
            "url": "https://api.github.com/repos/w3c/data-shapes/labels/i18n-comment",
            "name": "i18n-comment",
            "color": "d4c5f9",
            "default": false
          }
        ],
        "assignee": null,
        "isPullRequest": false
      },
      {
        "state": "closed",
        "number": 39,
        "created_at": "2017-03-16T17:21:32Z",
        "closed_at": "2017-03-17T04:16:21Z",
        "title": "RDF text strings & language",
        "labels": [
          {
            "id": 562399328,
            "url": "https://api.github.com/repos/w3c/data-shapes/labels/i18n-comment",
            "name": "i18n-comment",
            "color": "d4c5f9",
            "default": false
          },
          {
            "id": 561769025,
            "url": "https://api.github.com/repos/w3c/data-shapes/labels/No%20Action%20Required",
            "name": "No Action Required",
            "color": "d4c5f9",
            "default": false
          }
        ],
        "assignee": null,
        "isPullRequest": false
      },
      {
        "state": "closed",
        "number": 38,
        "created_at": "2017-03-16T01:15:14Z",
        "closed_at": "2017-03-16T03:15:35Z",
        "title": "SPARQL additions ",
        "labels": [
          {
            "id": 559868790,
            "url": "https://api.github.com/repos/w3c/data-shapes/labels/Commenter%20Satisfied",
            "name": "Commenter Satisfied",
            "color": "bfe5bf",
            "default": false
          },
          {
            "id": 559868791,
            "url": "https://api.github.com/repos/w3c/data-shapes/labels/Postponed%20(revisit%20in%20future%20effort)",
            "name": "Postponed (revisit in future effort)",
            "color": "cccccc",
            "default": false
          }
        ],
        "assignee": null,
        "isPullRequest": false
      },
      {
        "state": "closed",
        "number": 37,
        "created_at": "2017-03-14T22:47:40Z",
        "closed_at": "2017-03-14T23:02:09Z",
        "title": "ACTION-48 : some changes based on first review",
        "labels": [],
        "assignee": null,
        "isPullRequest": true
      },
      {
        "state": "open",
        "number": 36,
        "created_at": "2017-03-10T00:00:15Z",
        "closed_at": null,
        "title": "Ambiguity in examples",
        "labels": [
          {
            "id": 559868786,
            "url": "https://api.github.com/repos/w3c/data-shapes/labels/Editorial%20(would%20not%20change%20implementations)",
            "name": "Editorial (would not change implementations)",
            "color": "006b75",
            "default": false
          },
          {
            "id": 559868784,
            "url": "https://api.github.com/repos/w3c/data-shapes/labels/Waiting%20for%20Commenter",
            "name": "Waiting for Commenter",
            "color": "fbca04",
            "default": false
          }
        ],
        "assignee": null,
        "isPullRequest": false
      },
      {
        "state": "closed",
        "number": 35,
        "created_at": "2017-03-09T21:25:02Z",
        "closed_at": "2017-03-16T00:50:27Z",
        "title": "Inclusion of sh:phase and sh:Phase",
        "labels": [
          {
            "id": 559868790,
            "url": "https://api.github.com/repos/w3c/data-shapes/labels/Commenter%20Satisfied",
            "name": "Commenter Satisfied",
            "color": "bfe5bf",
            "default": false
          }
        ],
        "assignee": null,
        "isPullRequest": false
      },
      {
        "state": "closed",
        "number": 34,
        "created_at": "2017-03-09T15:37:01Z",
        "closed_at": "2017-03-21T01:54:31Z",
        "title": "Feedback : Shape Graphs Usage",
        "labels": [
          {
            "id": 561769025,
            "url": "https://api.github.com/repos/w3c/data-shapes/labels/No%20Action%20Required",
            "name": "No Action Required",
            "color": "d4c5f9",
            "default": false
          }
        ],
        "assignee": null,
        "isPullRequest": false
      },
      {
        "state": "closed",
        "number": 33,
        "created_at": "2017-03-09T14:54:07Z",
        "closed_at": "2017-03-21T01:54:31Z",
        "title": "Feedback: Evidence of interest in SHACL",
        "labels": [
          {
            "id": 561769025,
            "url": "https://api.github.com/repos/w3c/data-shapes/labels/No%20Action%20Required",
            "name": "No Action Required",
            "color": "d4c5f9",
            "default": false
          }
        ],
        "assignee": null,
        "isPullRequest": false
      },
      {
        "state": "open",
        "number": 32,
        "created_at": "2017-03-08T22:46:53Z",
        "closed_at": null,
        "title": "Problems editing SHACL with Protégé",
        "labels": [
          {
            "id": 559868787,
            "url": "https://api.github.com/repos/w3c/data-shapes/labels/Needs%20Group%20Input/Decision",
            "name": "Needs Group Input/Decision",
            "color": "0052cc",
            "default": false
          }
        ],
        "assignee": null,
        "isPullRequest": false
      },
      {
        "state": "closed",
        "number": 31,
        "created_at": "2017-03-07T09:31:21Z",
        "closed_at": "2017-03-07T22:31:06Z",
        "title": "rdf:List typo fix",
        "labels": [],
        "assignee": null,
        "isPullRequest": true
      },
      {
        "state": "closed",
        "number": 30,
        "created_at": "2017-03-07T09:25:26Z",
        "closed_at": "2017-03-07T22:35:15Z",
        "title": "ACTION-48: Produce a json-ld @context draft",
        "labels": [],
        "assignee": null,
        "isPullRequest": true
      },
      {
        "state": "closed",
        "number": 29,
        "created_at": "2017-03-07T01:27:36Z",
        "closed_at": "2017-03-07T22:00:21Z",
        "title": "sh:query non-normative?",
        "labels": [
          {
            "id": 559868790,
            "url": "https://api.github.com/repos/w3c/data-shapes/labels/Commenter%20Satisfied",
            "name": "Commenter Satisfied",
            "color": "bfe5bf",
            "default": false
          }
        ],
        "assignee": null,
        "isPullRequest": false
      },
      {
        "state": "closed",
        "number": 28,
        "created_at": "2017-03-06T10:54:02Z",
        "closed_at": "2017-03-06T22:58:20Z",
        "title": "Wrong predicate in sh:disjoint description",
        "labels": [
          {
            "id": 559868783,
            "url": "https://api.github.com/repos/w3c/data-shapes/labels/Commenter%20Timeout%20(assuming%20satisfied)",
            "name": "Commenter Timeout (assuming satisfied)",
            "color": "fef2c0",
            "default": false
          }
        ],
        "assignee": null,
        "isPullRequest": false
      },
      {
        "state": "closed",
        "number": 27,
        "created_at": "2017-03-03T20:42:41Z",
        "closed_at": "2017-03-21T01:54:31Z",
        "title": "Plans to use and implement",
        "labels": [
          {
            "id": 561769025,
            "url": "https://api.github.com/repos/w3c/data-shapes/labels/No%20Action%20Required",
            "name": "No Action Required",
            "color": "d4c5f9",
            "default": false
          }
        ],
        "assignee": null,
        "isPullRequest": false
      },
      {
        "state": "closed",
        "number": 26,
        "created_at": "2017-02-08T06:45:27Z",
        "closed_at": "2017-03-21T04:36:36Z",
        "title": "References not rendering (Firefox 51.0.1)",
        "labels": [
          {
            "id": 559868786,
            "url": "https://api.github.com/repos/w3c/data-shapes/labels/Editorial%20(would%20not%20change%20implementations)",
            "name": "Editorial (would not change implementations)",
            "color": "006b75",
            "default": false
          }
        ],
        "assignee": null,
        "isPullRequest": false
      },
      {
        "state": "closed",
        "number": 25,
        "created_at": "2016-12-21T17:42:28Z",
        "closed_at": "2017-03-03T05:55:34Z",
        "title": "Re 4.2.3 sh:nodeKind: add a notice about putting a constraint on nodes to be blank nodes",
        "labels": [
          {
            "id": 559868783,
            "url": "https://api.github.com/repos/w3c/data-shapes/labels/Commenter%20Timeout%20(assuming%20satisfied)",
            "name": "Commenter Timeout (assuming satisfied)",
            "color": "fef2c0",
            "default": false
          }
        ],
        "assignee": null,
        "isPullRequest": false
      },
      {
        "state": "closed",
        "number": 24,
        "created_at": "2016-12-21T16:50:43Z",
        "closed_at": "2017-03-03T05:55:49Z",
        "title": "Re 4.2.3 sh:nodeKind: provide an instance for the combination of all kinds",
        "labels": [
          {
            "id": 559868783,
            "url": "https://api.github.com/repos/w3c/data-shapes/labels/Commenter%20Timeout%20(assuming%20satisfied)",
            "name": "Commenter Timeout (assuming satisfied)",
            "color": "fef2c0",
            "default": false
          }
        ],
        "assignee": null,
        "isPullRequest": false
      },
      {
        "state": "closed",
        "number": 23,
        "created_at": "2016-11-09T15:44:26Z",
        "closed_at": "2017-03-16T00:32:47Z",
        "title": "validation filter ordering",
        "labels": [],
        "assignee": null,
        "isPullRequest": true
      },
      {
        "state": "closed",
        "number": 22,
        "created_at": "2016-10-30T08:14:56Z",
        "closed_at": "2017-03-16T00:34:55Z",
        "title": "examples use tabular summary",
        "labels": [],
        "assignee": null,
        "isPullRequest": true
      },
      {
        "state": "closed",
        "number": 21,
        "created_at": "2016-09-07T10:04:06Z",
        "closed_at": "2016-09-07T20:58:45Z",
        "title": "typo",
        "labels": [],
        "assignee": null,
        "isPullRequest": true
      },
      {
        "state": "closed",
        "number": 20,
        "created_at": "2016-09-07T09:29:04Z",
        "closed_at": "2016-09-07T20:48:29Z",
        "title": "typo",
        "labels": [],
        "assignee": null,
        "isPullRequest": true
      },
      {
        "state": "closed",
        "number": 19,
        "created_at": "2016-09-07T09:25:56Z",
        "closed_at": "2016-09-07T20:47:48Z",
        "title": "typo",
        "labels": [],
        "assignee": null,
        "isPullRequest": true
      },
      {
        "state": "closed",
        "number": 18,
        "created_at": "2016-04-23T20:36:24Z",
        "closed_at": "2016-04-27T15:05:27Z",
        "title": "Update index.html",
        "labels": [],
        "assignee": null,
        "isPullRequest": true
      },
      {
        "state": "closed",
        "number": 17,
        "created_at": "2016-04-21T20:07:30Z",
        "closed_at": "2016-04-23T13:57:56Z",
        "title": "Update index.html",
        "labels": [],
        "assignee": null,
        "isPullRequest": true
      },
      {
        "state": "closed",
        "number": 16,
        "created_at": "2016-04-20T00:03:03Z",
        "closed_at": "2016-04-20T06:41:54Z",
        "title": "Update index.html",
        "labels": [],
        "assignee": null,
        "isPullRequest": true
      },
      {
        "state": "closed",
        "number": 15,
        "created_at": "2016-02-11T03:27:40Z",
        "closed_at": "2016-02-11T03:27:48Z",
        "title": "ISSUE 92 partition constraint",
        "labels": [],
        "assignee": null,
        "isPullRequest": true
      },
      {
        "state": "closed",
        "number": 14,
        "created_at": "2016-01-22T02:43:01Z",
        "closed_at": "2016-01-22T02:47:04Z",
        "title": "updated definition for ISSUE-23",
        "labels": [],
        "assignee": null,
        "isPullRequest": true
      },
      {
        "state": "closed",
        "number": 13,
        "created_at": "2016-01-19T19:28:56Z",
        "closed_at": "2016-01-19T19:29:04Z",
        "title": "Implemented proposal for ISSUE-23",
        "labels": [],
        "assignee": null,
        "isPullRequest": true
      },
      {
        "state": "closed",
        "number": 12,
        "created_at": "2016-01-19T00:10:39Z",
        "closed_at": "2016-01-19T00:10:50Z",
        "title": "Implemented resolution on recursive shapes, ISSUE-22",
        "labels": [],
        "assignee": null,
        "isPullRequest": true
      },
      {
        "state": "closed",
        "number": 11,
        "created_at": "2016-01-18T23:38:39Z",
        "closed_at": "2016-01-18T23:38:51Z",
        "title": "Implemented resolution of ISSUE-49",
        "labels": [],
        "assignee": null,
        "isPullRequest": true
      },
      {
        "state": "closed",
        "number": 10,
        "created_at": "2015-12-16T12:02:01Z",
        "closed_at": "2015-12-16T12:02:17Z",
        "title": "Wrote shacl-vocab.ttl and generated HTML",
        "labels": [],
        "assignee": null,
        "isPullRequest": true
      },
      {
        "state": "closed",
        "number": 9,
        "created_at": "2015-12-01T14:06:24Z",
        "closed_at": "2015-12-02T20:58:22Z",
        "title": "minor mistake in spec - ex:unsinged",
        "labels": [
          {
            "id": 559868790,
            "url": "https://api.github.com/repos/w3c/data-shapes/labels/Commenter%20Satisfied",
            "name": "Commenter Satisfied",
            "color": "bfe5bf",
            "default": false
          }
        ],
        "assignee": null,
        "isPullRequest": false
      },
      {
        "state": "closed",
        "number": 8,
        "created_at": "2015-10-28T22:38:39Z",
        "closed_at": "2015-10-28T22:39:05Z",
        "title": "Separated definitions of sh:qualifiedMinCount and sh:qualifiedMaxCount",
        "labels": [],
        "assignee": null,
        "isPullRequest": true
      },
      {
        "state": "closed",
        "number": 7,
        "created_at": "2015-10-22T21:15:14Z",
        "closed_at": "2015-10-22T21:15:39Z",
        "title": "Define sh:minLength, sh:maxLength, sh:qualifiedMinCount, and sh:qualifiedMaxCount without reference to default values",
        "labels": [],
        "assignee": null,
        "isPullRequest": true
      },
      {
        "state": "closed",
        "number": 6,
        "created_at": "2015-10-15T16:30:50Z",
        "closed_at": "2015-10-15T16:31:42Z",
        "title": "Defined sh:minCount and sh:maxCount without mention of default values",
        "labels": [],
        "assignee": null,
        "isPullRequest": true
      },
      {
        "state": "closed",
        "number": 5,
        "created_at": "2015-10-15T15:44:26Z",
        "closed_at": "2015-10-15T15:46:17Z",
        "title": "Updated examples 3,4,5",
        "labels": [],
        "assignee": null,
        "isPullRequest": true
      },
      {
        "state": "closed",
        "number": 4,
        "created_at": "2015-08-14T11:15:25Z",
        "closed_at": "2017-03-03T05:54:36Z",
        "title": "Page not found for ldom.ttl",
        "labels": [
          {
            "id": 559868783,
            "url": "https://api.github.com/repos/w3c/data-shapes/labels/Commenter%20Timeout%20(assuming%20satisfied)",
            "name": "Commenter Timeout (assuming satisfied)",
            "color": "fef2c0",
            "default": false
          }
        ],
        "assignee": null,
        "isPullRequest": false
      },
      {
        "state": "closed",
        "number": 3,
        "created_at": "2015-06-04T06:31:56Z",
        "closed_at": "2017-03-03T05:54:57Z",
        "title": "what about reification?",
        "labels": [
          {
            "id": 559868783,
            "url": "https://api.github.com/repos/w3c/data-shapes/labels/Commenter%20Timeout%20(assuming%20satisfied)",
            "name": "Commenter Timeout (assuming satisfied)",
            "color": "fef2c0",
            "default": false
          }
        ],
        "assignee": null,
        "isPullRequest": false
      },
      {
        "state": "closed",
        "number": 2,
        "created_at": "2015-05-02T15:45:54Z",
        "closed_at": "2015-05-02T21:26:22Z",
        "title": "Fix typo",
        "labels": [],
        "assignee": null,
        "isPullRequest": true
      },
      {
        "state": "closed",
        "number": 1,
        "created_at": "2015-04-29T14:48:15Z",
        "closed_at": "2015-12-16T12:22:10Z",
        "title": "minor mistake in specification",
        "labels": [
          {
            "id": 559868783,
            "url": "https://api.github.com/repos/w3c/data-shapes/labels/Commenter%20Timeout%20(assuming%20satisfied)",
            "name": "Commenter Timeout (assuming satisfied)",
            "color": "fef2c0",
            "default": false
          }
        ],
        "assignee": null,
        "isPullRequest": false
      }
    ]
  }
}